Workbook

Sheet CAPA
B3: BIOCHAR CARBON NOVA ESPERANÇA
B5: Modelo Financeiro de Projeto
B6: Pirólise de Biomassa Residual de Eucalipto — Créditos de Carbono Voluntários
B9: INFORMAÇÕES DO PROJETO
B10: Projeto | C10: BCNE — Biochar Carbon Nova Esperança
B11: Tecnologia | C11: Pirólise lenta — Beston BST-30
B12: Horizonte | C12: 20 anos (2026–2045) + Ano 0 investimento (2025)
B13: Biomassa | C13: Resíduos lenhosos de colheita florestal (E. grandis × urophylla)
B14: Produto | C14: Créditos de carbono (Puro.Earth / EBC) + biochar (opcional)
B15: Localização | C15: Horto florestal — Nova Esperança
B16: Moeda | C16: R$ (Reais brasileiros) | Preço carbono em USD
B17: Versão do modelo | C17: v7 — Metodologia mássica Pincelli | Abril 2026
B18: Preparado por | C18: Astra Carbon
B19: Metodologia biomassa | C19: Pincelli et al. (2017) Scientia Forestalis v.45 n.115 — abordagem mássica direta
B21: ESTRUTURA DO MODELO
B22: PREMISSAS | C22: Inputs editáveis (azul) — cadeia de biomassa mássica, preços, energia, OPEX, financeiros
B23: CÁLCULO | C23: Cadeia biomassa → biochar → créditos certificáveis (20 anos)
B24: CAPEX | C24: Investimento inicial com breakdown e depreciação
B25: OPEX | C25: Custos operacionais variáveis e fixos projetados (20 anos)
B26: RECEITA | C26: Receita bruta/líquida: créditos de carbono + biochar opcional
B27: DRE_FCL | C27: Demonstrativo de resultado + Fluxo de caixa livre
B28: INDICADORES | C28: VPL, TIR, Payback, métricas operacionais ano-base
B29: SENSIBILIDADE | C29: Tabelas bidimensionais: TIR × preço × volume × CAPEX
B30: CENÁRIOS | C30: 4 cenários editáveis: Conservador, Base, Otimista, Premium
B31: ENERGIA | C31: Detalhamento de consumo e custo energético CEMIG A4 Azul
B32: DASHBOARD | C32: Gráficos dinâmicos: composição CAPEX, OPEX, EBITDA, FCL
B35: CONVENÇÕES DE FORMATAÇÃO
B36: Texto azul | C36: Input editável (hardcoded) — altere para cenários
B37: Texto preto | C37: Fórmula ou cálculo — NÃO editar
B38: Texto verde | C38: Link entre abas (cross-sheet reference)
B39: Fundo azul claro | C39: Célula de input
B40: Fundo amarelo claro | C40: Célula calculada
B42: DISCLAIMER: Este modelo é ferramenta de análise e não constitui recomendação de investimento.

Sheet INDICADORES
B1: INDICADORES FINANCEIROS | VPL, TIR, Payback
B3: VPL | C3: =DRE_FCL!E18+NPV(PREMISSAS!$C$101,DRE_FCL!F18:Y18) -> -1040546.1 | D3: TIR | E3: =IFERROR(IRR(DRE_FCL!E18:Y18),"N/D") -> 0.06945947 | J3: Helper: Ano | K3: FCL Desc. Acum.
J4: =DRE_FCL!E3 -> 2026 | K4: =DRE_FCL!E18/((1+PREMISSAS!$C$101)^0) -> -5498000
B5: PAYBACK (anos) | C5: =IFERROR(MATCH(TRUE,INDEX(DRE_FCL!F19:Y19>=0,0),0),">Horizonte") -> 11 | D5: CAPEX TOTAL | E5: =CAPEX!$C$16 -> 5498000 | J5: =DRE_FCL!F3 -> 2027 | K5: =K4+DRE_FCL!F18/((1+PREMISSAS!$C$101)^1) -> -4953165.2
B6: Payback Descontado (anos) | C6: =IFERROR(_xlfn.AGGREGATE(15,6,J4:J24/(K4:K24>=0),1)-PREMISSAS!$C$103,">Horizonte") -> >Horizonte | J6: =DRE_FCL!G3 -> 2028 | K6: =K5+DRE_FCL!G18/((1+PREMISSAS!$C$101)^2) -> -4469915.3
B7: RECEITA BRUTA MÉDIA (anual) | C7: =IFERROR(AVERAGE(DRE_FCL!F5:Y5),0) -> 2897370.5 | D7: EBITDA MÉDIO (anual) | E7: =IFERROR(AVERAGE(DRE_FCL!F8:Y8),0) -> 1013660 | J7: =DRE_FCL!H3 -> 2029 | K7: =K6+DRE_FCL!H18/((1+PREMISSAS!$C$101)^3) -> -4041556
J8: =DRE_FCL!I3 -> 2030 | K8: =K7+DRE_FCL!I18/((1+PREMISSAS!$C$101)^4) -> -3662100.8
B9: MARGEM EBITDA MÉDIA | C9: =IFERROR(E7/C7,0) -> 0.34985515 | D9: FCL TOTAL 20 ANOS | E9: =SUM(DRE_FCL!E18:Y18) -> 4519256.3 | J9: =DRE_FCL!J3 -> 2031 | K9: =K8+DRE_FCL!J18/((1+PREMISSAS!$C$101)^5) -> -3326198.3
J10: =DRE_FCL!K3 -> 2032 | K10: =K9+DRE_FCL!K18/((1+PREMISSAS!$C$101)^6) -> -3029065.8
B11: RESUMO OPERACIONAL — ANO BASE | J11: =DRE_FCL!L3 -> 2033 | K11: =K10+DRE_FCL!L18/((1+PREMISSAS!$C$101)^7) -> -2766430.3
B12: Alimentação do reator | C12: =CÁLCULO!F4 -> 3940.8425 | D12: t/ano | J12: =DRE_FCL!M3 -> 2034 | K12: =K11+DRE_FCL!M18/((1+PREMISSAS!$C$101)^8) -> -2534475.2
B13: Produção de biochar | C13: =CÁLCULO!F5 -> 1182.2528 | D13: t/ano | J13: =DRE_FCL!N3 -> 2035 | K13: =K12+DRE_FCL!N18/((1+PREMISSAS!$C$101)^9) -> -2329792.9
B14: Créditos certificáveis | C14: =CÁLCULO!F8 -> 3215.7275 | D14: tCO₂e | J14: =DRE_FCL!O3 -> 2036 | K14: =K13+DRE_FCL!O18/((1+PREMISSAS!$C$101)^10) -> -2149341.5
B15: Dias de operação efetiva | C15: =CÁLCULO!F9 -> 164.20177 | D15: dias | J15: =DRE_FCL!P3 -> 2037 | K15: =K14+DRE_FCL!P18/((1+PREMISSAS!$C$101)^11) -> -1985294.8
B16: Meses de calendário | C16: =CÁLCULO!F10 -> 6.5680709 | D16: meses | J16: =DRE_FCL!Q3 -> 2038 | K16: =K15+DRE_FCL!Q18/((1+PREMISSAS!$C$101)^12) -> -1836161.5
B17: Receita bruta carbono | C17: =RECEITA!F3 -> 2897370.5 | D17: R$ | J17: =DRE_FCL!R3 -> 2039 | K17: =K16+DRE_FCL!R18/((1+PREMISSAS!$C$101)^13) -> -1700585.7
B18: OPEX total | C18: =OPEX!F22 -> 1734535.5 | D18: R$ | J18: =DRE_FCL!S3 -> 2040 | K18: =K17+DRE_FCL!S18/((1+PREMISSAS!$C$101)^14) -> -1577335
B19: EBITDA | C19: =DRE_FCL!F8 -> 1162835 | D19: R$ | J19: =DRE_FCL!T3 -> 2041 | K19: =K18+DRE_FCL!T18/((1+PREMISSAS!$C$101)^15) -> -1465289
B20: FCL | C20: =DRE_FCL!F18 -> 599318.31 | D20: R$ | J20: =DRE_FCL!U3 -> 2042 | K20: =K19+DRE_FCL!U18/((1+PREMISSAS!$C$101)^16) -> -1363428.9
B21: Consumo elétrico (kWh/t ativo) | C21: =PREMISSAS!$C$48 -> 207.375 | D21: kWh/t | J21: =DRE_FCL!V3 -> 2043 | K21: =K20+DRE_FCL!V18/((1+PREMISSAS!$C$101)^17) -> -1270828.8
B22: Modalidade eletrica | C22: =PREMISSAS!$C$47 -> Cemig A4 Verde 360 kW | D22: contrato base | J22: =DRE_FCL!W3 -> 2044 | K22: =K21+DRE_FCL!W18/((1+PREMISSAS!$C$101)^18) -> -1186646.9
J23: =DRE_FCL!X3 -> 2045 | K23: =K22+DRE_FCL!X18/((1+PREMISSAS!$C$101)^19) -> -1110117.9
J24: =DRE_FCL!Y3 -> 2046 | K24: =K23+DRE_FCL!Y18/((1+PREMISSAS!$C$101)^20) -> -1040546.1

Sheet GLOSSÁRIO
B2: GLOSSÁRIO DE APRESENTAÇÃO — Termos técnicos, acrônimos e jargões do modelo BCNE
B3: Use este guia para antecipar perguntas. ⚠️ = ponto crítico que provavelmente será questionado.
B5: Termo / Acrônimo | C5: Onde aparece | D5: O que significa em linguagem simples | E5: Atenção / Resposta sugerida
B6: 1. METODOLOGIA E BIOMASSA
B7: Pirólise lenta | C7: CAPA, PREMISSAS A | D7: Aquecimento da biomassa a 400–700 °C sem oxigênio, transformando madeira em biochar (carvão vegetal estável).
B8: Biochar | C8: Modelo todo | D8: Carvão vegetal sólido produzido pela pirólise; estoca carbono por séculos quando aplicado ao solo.
B9: Metodologia mássica / Pincelli et al. (2017) | C9: PREMISSAS A, CAPA | D9: Abordagem que calcula resíduo florestal por massa (toneladas) em vez de volume (m³). Pincelli é o artigo científico de referência (Scientia Forestalis). | E9: ⚠️ Pode ser questionado por que escolheu essa metodologia. Resposta: é a referência acadêmica brasileira para E. grandis × urophylla, dá rastreabilidade auditável.
B10: E. grandis × E. urophylla (clone I144) | C10: PREMISSAS C6, CAPA | D10: Híbrido de eucalipto mais plantado no Brasil para celulose e energia. I144 é um clone comercial específico.
B11: Densidade básica do fuste | C11: PREMISSAS C6 | D11: Massa seca de madeira por m³ de tronco. Converte volume colhido em toneladas.
B12: Cominuição | C12: PREMISSAS A, C | D12: Trituração / moagem da biomassa em partículas menores antes de entrar no reator. | E12: Termo técnico — pode preferir dizer 'trituração' na fala.
B13: Fração lenhosa | C13: PREMISSAS C8 | D13: Parte do resíduo de campo que é madeira aproveitável (vs. folhas/casca fina que se perdem).
B14: Fuste | C14: PREMISSAS C6 | D14: Tronco principal da árvore (sem galhos e copa).
B15: Rendimento da pirólise | C15: PREMISSAS C28 | D15: % da biomassa seca que vira biochar. No modelo: 30% (de cada 1 t de madeira saem 300 kg de biochar). | E15: ⚠️ Pergunta provável: 'por que 30%?'. Resposta: faixa típica do BST-30 com madeira é 25–35%, base conservadora.
B17: 2. CRÉDITOS DE CARBONO E CERTIFICAÇÃO
B18: tCO₂e (toneladas de CO₂ equivalente) | C18: PREMISSAS B, INDICADORES | D18: Unidade padrão de crédito de carbono. 1 crédito = 1 tonelada de CO₂ evitada/sequestrada.
B19: Fator de carbono (2,72 tCO₂e/t biochar) | C19: PREMISSAS C32 | D19: Quanto CO₂ cada tonelada de biochar representa. Vem do carbono fixo × 44/12 (razão entre massa molecular de CO₂ e C). | E19: ⚠️ Se questionado o '44/12': átomo de carbono pesa 12, molécula de CO₂ pesa 44. É conversião estequiométrica padrão.
B20: C-loss / Desconto de permanência | D20: Desconto aplicado para refletir que parte do carbono pode degradar ao longo do tempo. Modelo usa 10%. | E20: ⚠️ Padrão exigido pelas certificadoras EBC/Puro.Earth (faixa 8–15%).
B21: EBC (European Biochar Certificate) | C21: PREMISSAS, CAPA | D21: Certificado europeu de biochar; estabelece padrões de qualidade e contabilidade de carbono.
B22: Puro.Earth | C22: PREMISSAS, CAPA | D22: Plataforma/registro de créditos de carbono de remoção de longa duração (carbon removal).
B23: MRV (Monitoring, Reporting & Verification) | C23: PREMISSAS F, CAPEX | D23: Sistema de Monitoramento, Relato e Verificação exigido para emitir créditos de carbono credíveis. | E23: ⚠️ Acrônimo crítico — explicar na primeira menção.
B24: ACV (Análise de Ciclo de Vida) | C24: PREMISSAS F | D24: Estudo que mede o impacto ambiental do projeto do berço ao tumulo (insumos, processo, transporte, uso final).
B25: LCA (Life Cycle Assessment) | C25: PREMISSAS D | D25: Mesmo que ACV — a sigla em inglês. 'Renovação LCA' = atualização anual da ACV exigida pela certificação. | E25: ⚠️ Aparece em inglês e português no mesmo modelo. Padronizar discurso.
B26: Mercado voluntário | C26: PREMISSAS C34 | D26: Compradores que adquirem créditos por escolha (ESG, net zero), não por obrigação regulatória. | E26: ⚠️ Pergunta provável: 'e o preço de USD 170/t é real?'. Faixa de remoção de alta qualidade (biochar/DAC) negocia entre USD 100–250.
B28: 3. ENERGIA E TARIFAS CEMIG
B29: Cemig A4 Verde | C29: PREMISSAS C, E | D29: Modalidade tarifária da Cemig para clientes industriais conectados em média tensão (2,3 a 25 kV). 'Verde' = tarifa única de demanda (sem distinção ponta/fora ponta na demanda). | E29: ⚠️ Pergunta crítica. Diferença vs. A4 Azul: Azul tem demanda separada para ponta e fora ponta; Verde tem demanda única + consumo diferenciado.
B30: Demanda contratada (kW) | C30: PREMISSAS E | D30: Potência que a empresa contrata firme com a Cemig. Paga mês a mês mesmo sem consumir. | E30: ⚠️ Custo fixo anual de 12 meses, mesmo operando 6 meses. Justificativa: contrato e infraestrutura de rede.
B31: Demanda de ultrapassagem | C31: PREMISSAS E | D31: Multa de 2x a tarifa quando o consumo excede a demanda contratada (>5% acima).
B32: Horário de ponta / fora ponta | C32: PREMISSAS E | D32: Ponta = 17h-20h em dias úteis (energia mais cara). Fora ponta = restante (mais barata). Modelo programa trituração fora de ponta.
B33: Gross-up de impostos (1,3113x) | C33: PREMISSAS E | D33: Multiplicador que converte tarifa 'sem impostos' em tarifa final paga (com ICMS, PIS, COFINS embutidos). | E33: Termo de engenharia tarifária. Em português: 'fator de bruto-líquido' ou simplesmente 'multiplicador de impostos'.
B34: kWh/t (consumo específico) | C34: PREMISSAS C, INDICADORES | D34: Energia elétrica gasta para processar 1 tonelada de biomassa. Modelo: 207 kWh/t.
B35: Roll-up por equipamento | C35: PREMISSAS C44, C45 | D35: Soma das potências por equipamento (britador, secador, reator) em vez de usar o número único do fornecedor. | E35: Termo do mundo de modelagem; pode dizer 'consolidação por equipamento'.
B36: Resolução Homologatória ANEEL 3.459/2025 | C36: PREMISSAS E | D36: Norma da agência reguladora que define as tarifas Cemig vigentes usadas no modelo.
B37: BST-30 (Beston) | C37: PREMISSAS A, F, CAPA | D37: Modelo do reator de pirólise comprado da fabricante chinesa Beston. Capacidade 1–1,5 t/h.
B38: Diesel S10 | C38: PREMISSAS E | D38: Diesel com baixo teor de enxofre (10 ppm), padrão brasileiro. Usado no aquecimento de partida do reator.
B39: QGBT / MT / BT / AT | C39: PREMISSAS F (Instalação elétrica) | D39: QGBT = Quadro Geral de Baixa Tensão. MT = Média Tensão. BT = Baixa Tensão. AT = Alta Tensão. | E39: ⚠️ Vários acrônimos juntos numa nota de célula (PREMISSAS!E97). Se alguém perguntar pelo CAPEX elétrico zerado, ter explicação pronta.
B41: 4. TRIBUTÁRIO
B42: Lucro Real | C42: PREMISSAS G, I, TRIBUTAÇÃO | D42: Regime de tributação no qual IRPJ e CSLL incidem sobre o lucro contábil ajustado, não sobre receita. | E42: ⚠️ Pergunta provável: 'por que Lucro Real e não Presumido?'. Resposta: receita projetada permite, e Lucro Real aproveita prejuízo fiscal nos primeiros anos.
B43: PIS / COFINS | C43: PREMISSAS I, TRIBUTAÇÃO | D43: Contribuições federais sobre receita. Lucro Real → regime não cumulativo (1,65% + 7,6%). | E43: ⚠️ Créditos de carbono: ZERO de PIS/COFINS pela Lei 15.042/2024 art. 19 — vantagem fiscal importante para destacar.
B44: IRPJ / CSLL | C44: PREMISSAS I, TRIBUTAÇÃO | D44: IRPJ = Imposto de Renda Pessoa Jurídica (15% + 10% adicional). CSLL = Contribuição Social sobre Lucro Líquido (9%).
B45: Lei 15.042/2024 | C45: PREMISSAS I | D45: Lei brasileira que regulamentou o mercado de carbono e desonerou de PIS/COFINS a alienação de créditos. | E45: ⚠️ Pode ser perguntado se isso é firme. Sim, está em lei sancionada. Apenas regulamentações operacionais pendentes.
B46: Prejuízo fiscal / Base negativa CSLL | C46: TRIBUTAÇÃO, PREMISSAS I | D46: Quando a empresa dá prejuízo, gera 'crédito fiscal' que abate impostos futuros, limitado a 30% do lucro do ano.
B47: SPE (Sociedade de Propósito Específico) | C47: PREMISSAS I | D47: Empresa criada apenas para o projeto. Isola riscos, facilita financiamento e governança.
B48: Adições / Exclusões fiscais | C48: PREMISSAS I, TRIBUTAÇÃO | D48: Ajustes ao lucro contábil para chegar ao lucro real (despesas não dedutíveis somam, receitas isentas subtraem).
B49: Crédito de PIS/COFINS | C49: PREMISSAS I, TRIBUTAÇÃO | D49: No regime não cumulativo, parte das despesas gera crédito que reduz o imposto a pagar. | E49: Modelo usa 0% de elegibilidade (premissa conservadora). Pode ser questionado: justificar como 'a definir com mapeamento de insumos'.
B51: 5. FINANCEIRO E VALUATION
B52: VPL (Valor Presente Líquido) | C52: INDICADORES | D52: Soma dos fluxos de caixa futuros trazidos a valor de hoje pela WACC. VPL > 0 → projeto cria valor. | E52: ⚠️ VPL atual = -R$ 398 mil (negativo). Ter narrativa pronta: próximo do break-even, sensível a preço de carbono.
B53: TIR (Taxa Interna de Retorno) | C53: INDICADORES | D53: Taxa de desconto que zera o VPL. É o 'retorno do projeto'. Modelo: 8,9%. | E53: ⚠️ TIR (8,9%) abaixo da WACC (10%) — explica VPL negativo. Coerente entre si.
B54: MIRR (TIR Modificada) | C54: INDICADORES | D54: Variante da TIR que assume reinvestimento dos fluxos à WACC (mais realista que TIR pura). | E54: MIRR = 9,6% > TIR = 8,9%, indica que TIR pura penaliza o projeto.
B55: WACC (Custo Médio Ponderado de Capital) | C55: PREMISSAS G | D55: Taxa de retorno mínima exigida considerando custo de equity e dívida ponderados. Modelo: 10%. | E55: ⚠️ Pergunta provável: 'como calculou 10%?'. Se for premissa, dizer claramente 'taxa-alvo do investidor', não cálculo CAPM.
B56: FCL (Fluxo de Caixa Livre) | C56: DRE_FCL | D56: Caixa que sobra após pagar OPEX, impostos e CAPEX. É o que efetivamente vai para o acionista.
B57: EBITDA | C57: DRE_FCL, INDICADORES | D57: Lucro antes de juros, impostos, depreciação e amortização. Proxy de geração de caixa operacional.
B58: EBIT | C58: DRE_FCL | D58: Lucro antes de juros e impostos (EBITDA menos depreciação).
B59: Depreciação | C59: DRE_FCL | D59: Reconhecimento contábil do desgaste dos ativos ao longo da vida útil. Não é saída de caixa.
B60: Payback / Payback Descontado | C60: INDICADORES | D60: Tempo para recuperar o CAPEX. Simples = soma de FCLs nominais. Descontado = traz fluxos a valor presente. | E60: ⚠️ Payback simples = 10 anos; descontado = '> horizonte' (não paga em 20 anos descontados). Coerente com VPL negativo.
B61: Capital de Giro / WC (Working Capital) | C61: DRE_FCL, PREMISSAS G | D61: Caixa imobilizado em recebíveis e estoques. Modelo tem toggle: caso-base = desligado. | E61: Se questionado: 'desligamos no caso-base; sensível ao prazo de recebimento dos créditos (6 meses)'.
B62: CAPEX / OPEX | C62: Modelo todo | D62: CAPEX = investimento (único, no Ano 0). OPEX = despesas operacionais recorrentes.
B63: Margem EBITDA | C63: INDICADORES | D63: EBITDA / Receita bruta. Modelo médio: 31,5%.
B64: Fee Astra Carbon | C64: PREMISSAS G, RECEITA | D64: Comissão da Astra (estruturadora) sobre receita bruta. Modelo: 0% no caso-base. | E64: ⚠️ Se for apresentar para a própria Astra, esclarecer por que está zerado.
B65: Toggle | C65: PREMISSAS | D65: Chave liga/desliga (1 ou 0) para ativar/desativar uma premissa no modelo (ex.: receita biochar, capital de giro). | E65: Anglicismo. Em português: 'chave' ou 'interruptor'.
B66: Hardcode / Hardcoded | C66: PREMISSAS C92, notas | D66: Valor digitado direto na célula (não vem de fórmula). Em finanças: 'input fixo'. | E66: Anglicismo. Pode dizer 'valor fixado' ou 'premissa direta'.
B67: Sanity check | C67: PREMISSAS C40 | D67: Verificação rápida de coerência (óbvio bate?). Não é cálculo do modelo, só conferência. | E67: Anglicismo. Pode dizer 'teste de coerência'.
B68: Off-peak firm | C68: PREMISSAS C92 | D68: Compromisso firme de operar fora de horário de ponta para reduzir custo de energia. | E68: Termo híbrido. Em português: 'operação firme fora de ponta'.
B69: Due diligence / Data room | C69: PREMISSAS F (notas) | D69: Due diligence = auditoria pré-investimento. Data room = repositório digital com documentos do projeto para o investidor analisar.

Sheet PREMISSAS
B1: PREMISSAS DO MODELO | Biochar Carbon Nova Esperança v7 — Metodologia Mássica
B2: Azul = input editável | Amarelo = calculado | Coluna E = fonte/referência auditável
B3: Premissa | C3: Valor | D3: Unidade | E3: Fonte / Referência
B4: A — CADEIA DE BIOMASSA (Abordagem Mássica — Pincelli et al., 2017)
B5: Volume de colheita anual | C5: 182690 | D5: m³/ano | E5: Área concessionada; referência campo 2024
B6: Densidade básica do fuste | C6: 0.48 | D6: t/m³ | E6: E. grandis × E. urophylla clone I144, 7 anos — lit. 0,44–0,50
B7: Fração mássica de resíduo de campo (%) | C7: 0.06 | D7: % | E7: Pincelli et al. (2017) Tab.1: 8,2 t/ha ÷ 136,4 t/ha = 6,0%. Resíduo total 60d pós-colheita.
B8: Fração lenhosa aproveitável (% resíduo) | C8: 0.749 | D8: % | E8: Pincelli et al. (2017) Tab.3: 74,9% madeira c/ casca no resíduo total
B9: Massa de produção (t/ano) | C9: =C5*C6 -> 87691.2 | D9: t/ano | E9: Calculado: volume colheita × densidade básica fuste
B10: Massa de resíduo bruto de campo (t/ano) | C10: =C9*C7 -> 5261.472 | D10: t/ano | E10: Calculado: massa produção × 6,0% (Pincelli 2017)
B11: Fração lenhosa seca disponível (t/ano) | C11: =C10*C8 -> 3940.8425 | D11: t/ano | E11: Calculado: resíduo bruto × 74,9% fração lenhosa
B12: Biomassa na porteira da planta (t/ano) | C12: =C11 -> 3940.8425 | D12: t/ano | E12: Após perda no transporte
B13: ALIMENTAÇÃO DO REATOR (t/ano) | C13: =C12 -> 3940.8425 | D13: t/ano | E13: Após cominuição — BASE de todo o modelo
B15: Ciclo Operacional do Reator (Beston BST-30)
B16: Dias de operação por ciclo | C16: 10 | D16: dias | E16: Beston: ciclo padrão operação contínua
B17: Dias de manutenção por ciclo | C17: 2 | D17: dias | E17: Limpeza + manutenção preventiva
B18: Disponibilidade efetiva do reator (%) | C18: =C16/(C16+C17) -> 0.83333333
B19: Capacidade do reator (t seca/h) | C19: 1 | D19: t/h | E19: Beston BST-30: 1,0–1,5 t/h; base conservadora
B20: Horas de operação por dia | C20: 24 | D20: h/dia | E20: Operação contínua — reator industrial
B21: Horas de operação efetiva/ano | C21: =C13/C19 -> 3940.8425 | D21: h/ano
B22: Dias de operação efetiva/ano | C22: =C21/C20 -> 164.20177 | D22: dias/ano | E22: Calculado: C15/C21/C22 (alimentação ÷ cap. reator ÷ h/dia). Alimenta: OPEX (mão de obra, manutenção), ENERGIA e indicadores operacionais.
B23: Dias de calendário necessários/ano | C23: =C22/C18 -> 197.04213 | D23: dias/ano
B24: Meses de calendário necessários/ano | C24: =C23/30 -> 6.5680709 | D24: meses/ano
B25: Número de ciclos de manutenção/ano | C25: =ROUNDUP(C22/C16,0) -> 17 | D25: ciclos | E25: Ciclos discretos: arredonda para cima para refletir startup/manutencao por ciclo inteiro.
B26: Rendimento da pirólise (%) | C26: 0.3 | D26: % | E26: Biochar/alimentação seca; BST-30+madeira: 25–35%. Base: 30%
B27: B — CRÉDITOS DE CARBONO E PREÇO
B28: Fator de carbono (tCO₂e / t biochar) | C28: 2.72 | D28: tCO₂e/t | E28: EBC/Puro.Earth — carbono fixo × 44/12
B30: Preço do crédito de carbono (USD/tCO₂e) | C30: 170 | D30: USD/tCO₂e | E30: Mercado voluntário — premissa base
B31: Taxa de câmbio USD/BRL | C31: 5.3 | D31: R$/USD | E31: Câmbio fixo — atualizar conforme cenário
B32: Preço de venda do biochar (R$/t) | C32: 0 | D32: R$/t | E32: Opcional — 0 = desligado
B33: Receita de biochar ativa? (1=Sim, 0=Não) | C33: 0 | D33: 1/0 | E33: Toggle: ativa/desativa linha de receita biochar
B35: C - ENERGIA ELETRICA | Contrato Cemig A4 Verde - Montes Claros/MG
B36: Operacao real contratada
B37: Capacidade cominuicao (t seca/h) | C37: 4 | D37: t/h | E37: Linha de cominuicao trabalha 6h/dia; capacidade nominal 3-5 t/h, base 4 t/h.
B38: Potencia media cominuicao | C38: 164.5 | D38: kW | E38: Roll-up fase 1: britagem/peneiramento + recirculacao media.
B39: Potencia media pirolise 24h | C39: 166.25 | D39: kW | E39: Roll-up fase 2: secador + reator + auxiliares.
B40: kWh/t cominuicao | C40: =C38/C37 -> 41.125 | D40: kWh/t
B41: kWh/t pirolise | C41: =C39/C19 -> 166.25 | D41: kWh/t
B42: Consumo especifico processo | C42: =C40+C41 -> 207.375 | D42: kWh/t | E42: Cominuicao 6h/dia + pirolise 24h/dia; secador tratado na pirolise.
B44: Consumo eletrico de startup por ciclo | C44: 120 | D44: kWh/ciclo | E44: Auxiliares eletricos de partida; aquecimento principal via diesel/gas.
B45: Overhead startup anual | C45: =C44*C25 -> 2040 | D45: kWh/ano
B47: Modalidade eletrica base | C47: Cemig A4 Verde 360 kW | D47: contrato | E47: Fixo no modelo: nao ha mais toggle de Modos A/B de eletricidade. Caso-base combina cominuicao fora ponta + gestao ativa de demanda.
B48: Consumo especifico processo (kWh/t) | C48: =C42 -> 207.375 | D48: kWh/t
B49: D — DIRECIONADORES DE OPEX
B50: Custo por operador (R$/mês) | C50: 6000 | D50: R$/mês | E50: Custo total com encargos
B51: Número de operadores | C51: 9 | D51: pessoas | E51: Escala com meses de operação
B52: O&M reator progressivo - taxa ano 1 | C52: 0.01 | D52: % | E52: OPEX!13 aplica 1% no ano 1, 2% no ano 2, ... ate 10% no ano 10+ sobre o CAPEX do reator BST-30 (CAPEX!C6/PREMISSAS!C88). Sem prorrata por meses de campanha.
B53: Logística de coleta (R$/t biomassa) | C53: 36 | D53: R$/t | E53: Custo de recolha no campo
B54: Logística de transporte (R$/t biomassa) | C54: 60 | D54: R$/t | E54: Frete até a planta
B55: Auditoria e verificação anual (R$/ano) | C55: 100000 | D55: R$/ano | E55: Fixo anual de existencia do projeto
B56: Renovação LCA + relatório (R$/ano) | C56: 35000 | D56: R$/ano | E56: Fixo anual de existencia do projeto
B57: Big bags e embalagem (R$/t biochar) | C57: 21.37 | D57: R$/t biochar | E57: Taxa de mercado: ~R$21,37/t biochar (big bags industriais ~500 kg). ATENÇÃO: nota histórica dizia R$28.000/ano ÷ 1.310t (biomassa anterior). Com produção atual ~1.078t: custo anual ≈ R$23.037. Se orçamento-alvo for R$28.000/ano → taxa correta = R$25,97/t. Confirmar com engenharia.
B58: Material de laboratório (R$/t biochar) | C58: 30.53 | D58: R$/t biochar | E58: Taxa de mercado: ~R$30,53/t biochar (análises QC laboratoriais EBC/Puro.Earth). ATENÇÃO: nota histórica dizia R$40.000/ano ÷ 1.310t (biomassa anterior). Com produção atual ~1.078t: custo anual ≈ R$32.931. Se orçamento-alvo for R$40.000/ano → taxa correta = R$37,11/t. Confirmar com engenharia.
B59: Treinamento e outros fixos (R$/ano) | C59: 10000 | D59: R$/ano | E59: Fixo anual de existencia do projeto
B61: E - TARIFAS CEMIG A4 VERDE (vigentes Res. Hom. ANEEL 3.459/2025)
B62: Demanda contratada Cemig | C62: 360 | D62: kW | E62: Contrato assinado para 360 kW; obra de rede dimensionada para esta potencia.
B63: Tarifa demanda unica - sem impostos | C63: 22.81 | D63: R$/kW mes | E63: Cemig A4 Verde, bandeira verde, antes de impostos.
B64: Tarifa consumo ponta - sem impostos | C64: 2.28496 | D64: R$/kWh | E64: Cemig A4 Verde, antes de impostos.
B65: Tarifa consumo fora ponta - sem impostos | C65: 0.45 | D65: R$/kWh | E65: Cemig A4 Verde, antes de impostos.
B66: Dias uteis por semana | C66: 5 | D66: dias/sem | E66: Ponta considerada apenas em dias uteis; fins de semana e feriados entram como fora ponta.
B67: Horas de ponta por dia util | C67: 3 | D67: h/dia | E67: Cemig: 17h-20h em dias uteis; validar eventual excecao contratual/local na fatura.
B68: ICMS energia MG | C68: 0.18 | D68: % | E68: Premissa base industrial/comercial MG; revisar com contador para creditamento e enquadramento fiscal.
B69: PIS/PASEP Cemig | C69: 0.0125 | D69: % | E69: Tabela Cemig PIS/COFINS Mar/2026: PASEP 1,25%. Atualizar mensalmente pela fatura.
B70: COFINS Cemig | C70: 0.0575 | D70: % | E70: Tabela Cemig PIS/COFINS Mar/2026: COFINS 5,75%. Atualizar mensalmente pela fatura.
B71: Fator gross-up impostos | C71: =1/(1-C69-C70)/(1-C68) -> 1.3113034 | D71: x | E71: Replica fator Cemig Mar/2026 com ICMS 18%: ~1,3113.
B72: Demanda unica com impostos | C72: =C63*C71 -> 29.910831 | D72: R$/kW mes
B73: Consumo ponta com impostos | C73: =C64*C71 -> 2.9962759 | D73: R$/kWh
B74: Consumo fora ponta com impostos | C74: =C65*C71 -> 0.59008655 | D74: R$/kWh
B75: Fracao media de dias uteis | C75: =C66/7 -> 0.71428571 | D75: %
B76: Fracao ponta da pirolise 24h | C76: =C67*C75/24 -> 0.089285714 | D76: % | E76: Media anual sem calendario de feriados; conservadora porque nao desconta feriados nacionais.
B77: Cominuição sempre fora ponta (consolidado) | C77: 0 | D77: Premissa operacional — off-peak firm. C92 hardcoded. | E77: Caso-base combinado: 0. Cominuicao programada fora de ponta para reduzir custo A4 Verde.
B78: Tarifa efetiva consumo medio | C78: =IF((C40+C41+IF(C13>0,C45/C13,0))>0,(C40*C74+C41*C76*C73+C41*(1-C76)*C74+IF(C13>0,C45/C13,0)*C74)/(C40+C41+IF(C13>0,C45/C13,0)),0) -> 0.76189095 | D78: R$/kWh | E78: Media ponderada com impostos por perfil de operacao: pirolise 24h e cominuicao 6h/dia fora ponta.
B79: Demanda mensal contratada com impostos | C79: =C62*C72 -> 10767.899 | D79: R$/mes | E79: Custo mensal de demanda ativa = kW contratado x tarifas de demanda ponta e fora ponta.
B80: Consumo diesel startup (L/ciclo) | C80: 178 | D80: L/ciclo | E80: Beston BST-30 proposta p.4: 130-155 L/h x 1,0-1,5h; media adotada 178 L/ciclo.
B81: Preco diesel S10 | C81: 6.5 | D81: R$/L | E81: ANP/referencia MG industrial — abril 2026
B82: Custo anual diesel startup | C82: =C25*C80*C81 -> 19669 | D82: R$/ano | E82: Ciclos/ano x L/ciclo x R$/L
B84: F — COMPONENTES DO CAPEX
B85: Instalação elétrica | C85: 0 | D85: R$ | E85: R$0 — custo 100% alocado à CEMIG por contrato. Obra de ramal MT/AT, QGBT, proteção seletiva, transformador e medição são de responsabilidade contratual da CEMIG como condição da conexão A4 Verde 360 kW. Documentar cláusula contratual específica no data room para due diligence.
B86: Terraplanagem e drenagem | C86: 300000 | D86: R$
B87: Infraestrutura civil | C87: 400000 | D87: R$
B88: Aquisição do reator BST-30 | C88: 2210000 | D88: R$
B89: Linha de cominuição / triturador | C89: 240000 | D89: R$
B90: Secador de biomassa | C90: 150000 | D90: R$
B91: Frete + seguro + sobressalentes | C91: 312000 | D91: R$
B92: Montagem e comissionamento | C92: 450000 | D92: R$
B93: Pequena Subestacao de energia | C93: 400000 | D93: R$ | E93: Infraestrutura electrica cliente; transformador, QG, protecao e cabeamento MT/BT
B94: Análise de Ciclo de Vida — ACV | C94: 45000 | D94: R$
B95: Plano de MRV e data room | C95: 150000 | D95: R$
B96: Auditoria inicial / certificação | C96: 100000 | D96: R$
B97: Serviços Astra Carbon | C97: =IF(C102>0,0,'Serviços Astra Carbon'!D52) -> 741000 | D97: R$
B99: G — PARÂMETROS FINANCEIROS
B100: Vida útil depreciação — físico (anos) | C100: 20 | D100: anos | E100: Linear; equipamentos + obras
B101: Taxa de desconto / WACC (%) | C101: 0.1 | D101: % | E101: Custo médio ponderado de capital
B102: Participação Astra Carbon (% receita) | C102: 0 | D102: % | E102: Fee sobre receita bruta
B103: Ano do investimento (Ano 0) | C103: 2026 | D103: ano | E103: CAPEX alocado neste ano
B104: Primeiro ano de operação | C104: 2027 | D104: ano | E104: Operação comercial inicia
B105: Meses de demanda eletrica fixa | C105: 12 | D105: meses/ano | E105: Fixo no caso-base: demanda contratada 360 kW faturada durante todo o ano. Consumo eletrico ocorre somente nos meses de operacao.
B106: Prazo recebimento créditos carbono (meses) | C106: 6 | D106: meses | E106: Ciclo verificação + liquidação
B107: Considerar capital de giro no FCL? (1=Sim, 0=Não) | C107: 0 | D107: 1/0 | E107: 1=aplica WC inicial (prazo × receita/12) no Ano 0. 0=desativa WC no FCL (caso-base atual). Toggle de simulação.
B108: I - PARAMETROS TRIBUTARIOS
...

Sheet CÁLCULO
B1: CÁLCULO | Cadeia Biomassa → Biochar → Créditos
B2: Metodologia mássica (Pincelli 2017). Ano 0 = investimento, Anos 1–20 = operação.
B3: Variável | C3: Unidade | D3: Referência | E3: 2026 | F3: 2027 | G3: 2028 | H3: 2029 | I3: 2030 | J3: 2031 | K3: 2032 | L3: 2033 | M3: 2034 | N3: 2035 | O3: 2036 | P3: 2037 | Q3: 2038 | R3: 2039 | S3: 2040 | T3: 2041 | U3: 2042 | V3: 2043 | W3: 2044 | X3: 2045 | Y3: 2046
B4: Alimentação do reator | C4: t/ano | D4: PREMISSAS — cadeia mássica | E4: 0 | F4: =PREMISSAS!$C$13 -> 3940.8425 | G4: =PREMISSAS!$C$13 -> 3940.8425 | H4: =PREMISSAS!$C$13 -> 3940.8425 | I4: =PREMISSAS!$C$13 -> 3940.8425 | J4: =PREMISSAS!$C$13 -> 3940.8425 | K4: =PREMISSAS!$C$13 -> 3940.8425 | L4: =PREMISSAS!$C$13 -> 3940.8425 | M4: =PREMISSAS!$C$13 -> 3940.8425 | ... Y4: =PREMISSAS!$C$13 -> 3940.8425
B5: Produção de biochar | C5: t/ano | D5: bio × rend | E5: 0 | F5: =F4*PREMISSAS!$C$26 -> 1182.2528 | G5: =G4*PREMISSAS!$C$26 -> 1182.2528 | H5: =H4*PREMISSAS!$C$26 -> 1182.2528 | I5: =I4*PREMISSAS!$C$26 -> 1182.2528 | J5: =J4*PREMISSAS!$C$26 -> 1182.2528 | K5: =K4*PREMISSAS!$C$26 -> 1182.2528 | L5: =L4*PREMISSAS!$C$26 -> 1182.2528 | M5: =M4*PREMISSAS!$C$26 -> 1182.2528 | ... Y5: =Y4*PREMISSAS!$C$26 -> 1182.2528
B6: Carbono fixado bruto | C6: tCO₂e | D6: biochar × fc | E6: 0 | F6: =F5*PREMISSAS!$C$28 -> 3215.7275 | G6: =G5*PREMISSAS!$C$28 -> 3215.7275 | H6: =H5*PREMISSAS!$C$28 -> 3215.7275 | I6: =I5*PREMISSAS!$C$28 -> 3215.7275 | J6: =J5*PREMISSAS!$C$28 -> 3215.7275 | K6: =K5*PREMISSAS!$C$28 -> 3215.7275 | L6: =L5*PREMISSAS!$C$28 -> 3215.7275 | M6: =M5*PREMISSAS!$C$28 -> 3215.7275 | ... Y6: =Y5*PREMISSAS!$C$28 -> 3215.7275
B8: CRÉDITOS LÍQUIDOS CERTIFICÁVEIS | C8: tCO₂e | D8: bruto − closs | E8: 0 | F8: =F6-F7 -> 3215.7275 | G8: =G6-G7 -> 3215.7275 | H8: =H6-H7 -> 3215.7275 | I8: =I6-I7 -> 3215.7275 | J8: =J6-J7 -> 3215.7275 | K8: =K6-K7 -> 3215.7275 | L8: =L6-L7 -> 3215.7275 | M8: =M6-M7 -> 3215.7275 | ... Y8: =Y6-Y7 -> 3215.7275
B9: Dias de operação efetiva | C9: dias/ano | D9: PREMISSAS | E9: 0 | F9: =PREMISSAS!$C$22 -> 164.20177 | G9: =PREMISSAS!$C$22 -> 164.20177 | H9: =PREMISSAS!$C$22 -> 164.20177 | I9: =PREMISSAS!$C$22 -> 164.20177 | J9: =PREMISSAS!$C$22 -> 164.20177 | K9: =PREMISSAS!$C$22 -> 164.20177 | L9: =PREMISSAS!$C$22 -> 164.20177 | M9: =PREMISSAS!$C$22 -> 164.20177 | ... Y9: =PREMISSAS!$C$22 -> 164.20177
B10: Meses de calendário | C10: meses/ano | D10: PREMISSAS | E10: 0 | F10: =PREMISSAS!$C$24 -> 6.5680709 | G10: =PREMISSAS!$C$24 -> 6.5680709 | H10: =PREMISSAS!$C$24 -> 6.5680709 | I10: =PREMISSAS!$C$24 -> 6.5680709 | J10: =PREMISSAS!$C$24 -> 6.5680709 | K10: =PREMISSAS!$C$24 -> 6.5680709 | L10: =PREMISSAS!$C$24 -> 6.5680709 | M10: =PREMISSAS!$C$24 -> 6.5680709 | ... Y10: =PREMISSAS!$C$24 -> 6.5680709

Sheet CAPEX
B1: CAPEX | Investimento Inicial e Depreciação
B2: Componente | C2: Valor (R$) | D2: % Total | E2: Fonte
B3: Instalação elétrica | C3: =PREMISSAS!C85 -> 0 | D3: =IF($C$16>0,C3/$C$16,0) -> 0 | E3: Grid + distribuição interna
B4: Terraplanagem e drenagem | C4: =PREMISSAS!C86 -> 300000 | D4: =IF($C$16>0,C4/$C$16,0) -> 0.054565296 | E4: Preparo do sítio
B5: Infraestrutura civil | C5: =PREMISSAS!C87 -> 400000 | D5: =IF($C$16>0,C5/$C$16,0) -> 0.072753729 | E5: Galpões, cercamento, acesso
B6: Reator de pirólise BST-30 | C6: =PREMISSAS!C88 -> 2210000 | D6: =IF($C$16>0,C6/$C$16,0) -> 0.40196435 | E6: Equipamento principal importado
B7: Linha de cominuição / triturador | C7: =PREMISSAS!C89 -> 240000 | D7: =IF($C$16>0,C7/$C$16,0) -> 0.043652237 | E7: Picador + moinho de martelos
B8: Secador de biomassa | C8: =PREMISSAS!C90 -> 150000 | D8: =IF($C$16>0,C8/$C$16,0) -> 0.027282648 | E8: Pré-tratamento de umidade
B9: Frete + seguro + sobressalentes | C9: =PREMISSAS!C91 -> 312000 | D9: =IF($C$16>0,C9/$C$16,0) -> 0.056747908 | E9: Importação + logística
B10: Montagem e comissionamento | C10: =PREMISSAS!C92 -> 450000 | D10: =IF($C$16>0,C10/$C$16,0) -> 0.081847945 | E10: Engenheiro Beston + equipe local
B11: Pequena Subestacao de energia | C11: =PREMISSAS!C93 -> 400000 | D11: =IF($C$16>0,C11/$C$16,0) -> 0.072753729 | E11: Transformador, QG, protecao e cabeamento MT/BT
B12: Análise de Ciclo de Vida (ACV) | C12: =PREMISSAS!C94 -> 45000 | D12: =IF($C$16>0,C12/$C$16,0) -> 0.0081847945 | E12: Parceria Gron — ACV inicial
B13: Plano de MRV e data room | C13: =PREMISSAS!C95 -> 150000 | D13: =IF($C$16>0,C13/$C$16,0) -> 0.027282648 | E13: Framework + estrutura documental
B14: Auditoria e certificação inicial | C14: =PREMISSAS!C96 -> 100000 | D14: =IF($C$16>0,C14/$C$16,0) -> 0.018188432 | E14: Validação de 3ª parte
B15: Serviços Astra Carbon | C15: =PREMISSAS!C97 -> 741000 | D15: =IF($C$16>0,C15/$C$16,0) -> 0.13477628 | E15: Originação+ Desenvolvimento + Certficação
B16: CAPEX TOTAL | C16: =SUM(C3:C15) -> 5498000
B18: DEPRECIAÇÃO | E18: NOTA: Linha C22 é valor de referência. Depreciação real por ano em E22:Y22 (zera após vida útil).
B19: CAPEX Físico | C19: =C3+C4+C5+C6+C7+C8+C9+C10+C11 -> 4462000 | D19: =IF($C$16>0,C19/$C$16,0) -> 0.81156784
E21: 2026 | F21: 2027 | G21: 2028 | H21: 2029 | I21: 2030 | J21: 2031 | K21: 2032 | L21: 2033 | M21: 2034 | N21: 2035 | O21: 2036 | P21: 2037 | Q21: 2038 | R21: 2039 | S21: 2040 | T21: 2041 | U21: 2042 | V21: 2043 | W21: 2044 | X21: 2045 | Y21: 2046
B22: Depreciação anual — Ano 1 ref. | C22: =IF(PREMISSAS!C100>0,C19/PREMISSAS!C100,0) -> 223100 | E22: =IF(AND(2026>=PREMISSAS!$C$104,2026<PREMISSAS!$C$104+PREMISSAS!$C$100),IF(PREMISSAS!$C$100>0,$C$19/PREMISSAS!$C$100,0),0) -> 0 | F22: =IF(AND(2027>=PREMISSAS!$C$104,2027<PREMISSAS!$C$104+PREMISSAS!$C$100),IF(PREMISSAS!$C$100>0,$C$19/PREMISSAS!$C$100,0),0) -> 223100 | G22: =IF(AND(2028>=PREMISSAS!$C$104,2028<PREMISSAS!$C$104+PREMISSAS!$C$100),IF(PREMISSAS!$C$100>0,$C$19/PREMISSAS!$C$100,0),0) -> 223100 | H22: =IF(AND(2029>=PREMISSAS!$C$104,2029<PREMISSAS!$C$104+PREMISSAS!$C$100),IF(PREMISSAS!$C$100>0,$C$19/PREMISSAS!$C$100,0),0) -> 223100 | I22: =IF(AND(2030>=PREMISSAS!$C$104,2030<PREMISSAS!$C$104+PREMISSAS!$C$100),IF(PREMISSAS!$C$100>0,$C$19/PREMISSAS!$C$100,0),0) -> 223100 | J22: =IF(AND(2031>=PREMISSAS!$C$104,2031<PREMISSAS!$C$104+PREMISSAS!$C$100),IF(PREMISSAS!$C$100>0,$C$19/PREMISSAS!$C$100,0),0) -> 223100 | K22: =IF(AND(2032>=PREMISSAS!$C$104,2032<PREMISSAS!$C$104+PREMISSAS!$C$100),IF(PREMISSAS!$C$100>0,$C$19/PREMISSAS!$C$100,0),0) -> 223100 | L22: =IF(AND(2033>=PREMISSAS!$C$104,2033<PREMISSAS!$C$104+PREMISSAS!$C$100),IF(PREMISSAS!$C$100>0,$C$19/PREMISSAS!$C$100,0),0) -> 223100 | M22: =IF(AND(2034>=PREMISSAS!$C$104,2034<PREMISSAS!$C$104+PREMISSAS!$C$100),IF(PREMISSAS!$C$100>0,$C$19/PREMISSAS!$C$100,0),0) -> 223100 | N22: =IF(AND(2035>=PREMISSAS!$C$104,2035<PREMISSAS!$C$104+PREMISSAS!$C$100),IF(PREMISSAS!$C$100>0,$C$19/PREMISSAS!$C$100,0),0) -> 223100 | O22: =IF(AND(2036>=PREMISSAS!$C$104,2036<PREMISSAS!$C$104+PREMISSAS!$C$100),IF(PREMISSAS!$C$100>0,$C$19/PREMISSAS!$C$100,0),0) -> 223100 | P22: =IF(AND(2037>=PREMISSAS!$C$104,2037<PREMISSAS!$C$104+PREMISSAS!$C$100),IF(PREMISSAS!$C$100>0,$C$19/PREMISSAS!$C$100,0),0) -> 223100 | Q22: =IF(AND(2038>=PREMISSAS!$C$104,2038<PREMISSAS!$C$104+PREMISSAS!$C$100),IF(PREMISSAS!$C$100>0,$C$19/PREMISSAS!$C$100,0),0) -> 223100 | R22: =IF(AND(2039>=PREMISSAS!$C$104,2039<PREMISSAS!$C$104+PREMISSAS!$C$100),IF(PREMISSAS!$C$100>0,$C$19/PREMISSAS!$C$100,0),0) -> 223100 | S22: =IF(AND(2040>=PREMISSAS!$C$104,2040<PREMISSAS!$C$104+PREMISSAS!$C$100),IF(PREMISSAS!$C$100>0,$C$19/PREMISSAS!$C$100,0),0) -> 223100 | T22: =IF(AND(2041>=PREMISSAS!$C$104,2041<PREMISSAS!$C$104+PREMISSAS!$C$100),IF(PREMISSAS!$C$100>0,$C$19/PREMISSAS!$C$100,0),0) -> 223100 | U22: =IF(AND(2042>=PREMISSAS!$C$104,2042<PREMISSAS!$C$104+PREMISSAS!$C$100),IF(PREMISSAS!$C$100>0,$C$19/PREMISSAS!$C$100,0),0) -> 223100 | V22: =IF(AND(2043>=PREMISSAS!$C$104,2043<PREMISSAS!$C$104+PREMISSAS!$C$100),IF(PREMISSAS!$C$100>0,$C$19/PREMISSAS!$C$100,0),0) -> 223100 | W22: =IF(AND(2044>=PREMISSAS!$C$104,2044<PREMISSAS!$C$104+PREMISSAS!$C$100),IF(PREMISSAS!$C$100>0,$C$19/PREMISSAS!$C$100,0),0) -> 223100 | X22: =IF(AND(2045>=PREMISSAS!$C$104,2045<PREMISSAS!$C$104+PREMISSAS!$C$100),IF(PREMISSAS!$C$100>0,$C$19/PREMISSAS!$C$100,0),0) -> 223100 | Y22: =IF(AND(2046>=PREMISSAS!$C$104,2046<PREMISSAS!$C$104+PREMISSAS!$C$100),IF(PREMISSAS!$C$100>0,$C$19/PREMISSAS!$C$100,0),0) -> 223100
B24: Depreciação anual (D&A) — lida pela DRE_FCL | C24: =C22 -> 223100 | E24: =E22 -> 0 | F24: =F22 -> 223100 | G24: =G22 -> 223100 | H24: =H22 -> 223100 | I24: =I22 -> 223100 | J24: =J22 -> 223100 | K24: =K22 -> 223100 | L24: =L22 -> 223100 | ... Y24: =Y22 -> 223100
B26: Vida útil | C26: =PREMISSAS!C100 -> 20 | D26: anos

Sheet RECEITA
B1: RECEITA | Créditos de Carbono + Venda Opcional de Biochar
B2: Linha de Receita | C2: Fórmula | D2: Referência | E2: 2026 | F2: 2027 | G2: 2028 | H2: 2029 | I2: 2030 | J2: 2031 | K2: 2032 | L2: 2033 | M2: 2034 | N2: 2035 | O2: 2036 | P2: 2037 | Q2: 2038 | R2: 2039 | S2: 2040 | T2: 2041 | U2: 2042 | V2: 2043 | W2: 2044 | X2: 2045 | Y2: 2046
B3: Receita créditos carbono (tCO₂e × USD × fx) | C3: créditos×USD×fx | D3: cred×preço×fx | E3: 0 | F3: =CÁLCULO!F8*PREMISSAS!$C$30*PREMISSAS!$C$31 -> 2897370.5 | G3: =CÁLCULO!G8*PREMISSAS!$C$30*PREMISSAS!$C$31 -> 2897370.5 | H3: =CÁLCULO!H8*PREMISSAS!$C$30*PREMISSAS!$C$31 -> 2897370.5 | I3: =CÁLCULO!I8*PREMISSAS!$C$30*PREMISSAS!$C$31 -> 2897370.5 | J3: =CÁLCULO!J8*PREMISSAS!$C$30*PREMISSAS!$C$31 -> 2897370.5 | K3: =CÁLCULO!K8*PREMISSAS!$C$30*PREMISSAS!$C$31 -> 2897370.5 | L3: =CÁLCULO!L8*PREMISSAS!$C$30*PREMISSAS!$C$31 -> 2897370.5 | M3: =CÁLCULO!M8*PREMISSAS!$C$30*PREMISSAS!$C$31 -> 2897370.5 | ... Y3: =CÁLCULO!Y8*PREMISSAS!$C$30*PREMISSAS!$C$31 -> 2897370.5
B4: Receita biochar (toggle × t × R$/t) | C4: toggle×t×R$/t | D4: toggle×bchar×preço | E4: 0 | F4: =PREMISSAS!$C$33*CÁLCULO!F5*PREMISSAS!$C$32 -> 0 | G4: =PREMISSAS!$C$33*CÁLCULO!G5*PREMISSAS!$C$32 -> 0 | H4: =PREMISSAS!$C$33*CÁLCULO!H5*PREMISSAS!$C$32 -> 0 | I4: =PREMISSAS!$C$33*CÁLCULO!I5*PREMISSAS!$C$32 -> 0 | J4: =PREMISSAS!$C$33*CÁLCULO!J5*PREMISSAS!$C$32 -> 0 | K4: =PREMISSAS!$C$33*CÁLCULO!K5*PREMISSAS!$C$32 -> 0 | L4: =PREMISSAS!$C$33*CÁLCULO!L5*PREMISSAS!$C$32 -> 0 | M4: =PREMISSAS!$C$33*CÁLCULO!M5*PREMISSAS!$C$32 -> 0 | ... Y4: =PREMISSAS!$C$33*CÁLCULO!Y5*PREMISSAS!$C$32 -> 0
B5: RECEITA BRUTA TOTAL | D5: carb+bchar | E5: 0 | F5: =F3+F4 -> 2897370.5 | G5: =G3+G4 -> 2897370.5 | H5: =H3+H4 -> 2897370.5 | I5: =I3+I4 -> 2897370.5 | J5: =J3+J4 -> 2897370.5 | K5: =K3+K4 -> 2897370.5 | L5: =L3+L4 -> 2897370.5 | M5: =M3+M4 -> 2897370.5 | ... Y5: =Y3+Y4 -> 2897370.5
B6: (–) Fee Astra Carbon (% receita bruta) | C6: % × bruta | D6: astra×bruta | E6: 0 | F6: =-F5*PREMISSAS!$C$102 -> 0 | G6: =-G5*PREMISSAS!$C$102 -> 0 | H6: =-H5*PREMISSAS!$C$102 -> 0 | I6: =-I5*PREMISSAS!$C$102 -> 0 | J6: =-J5*PREMISSAS!$C$102 -> 0 | K6: =-K5*PREMISSAS!$C$102 -> 0 | L6: =-L5*PREMISSAS!$C$102 -> 0 | M6: =-M5*PREMISSAS!$C$102 -> 0 | ... Y6: =-Y5*PREMISSAS!$C$102 -> 0
B7: (removida — receita líquida calculada no DRE_FCL) | D7: bruta+astra

Sheet TRIBUTAÇÃO
B1: TRIBUTOS - LUCRO REAL
A2: PIS/COFINS sobre créditos de carbono: 9,25% (1,65% PIS + 7,6% COFINS) — sem isenção | B2: Creditos de carbono: sem incidencia de PIS/COFINS na alienacao (Lei 15.042/2024, art. 19). IRPJ/CSLL sobre lucro real anual com compensacao de prejuizo fiscal e base negativa de CSLL.
B3: Item | C3: Origem | D3: Referencia | E3: 2026 | F3: 2027 | G3: 2028 | H3: 2029 | I3: 2030 | J3: 2031 | K3: 2032 | L3: 2033 | M3: 2034 | N3: 2035 | O3: 2036 | P3: 2037 | Q3: 2038 | R3: 2039 | S3: 2040 | T3: 2041 | U3: 2042 | V3: 2043 | W3: 2044 | X3: 2045 | Y3: 2046
B4: Receita creditos carbono | C4: RECEITA | D4: -> RECEITA!3 | E4: =RECEITA!E3 -> 0 | F4: =RECEITA!F3 -> 2897370.5 | G4: =RECEITA!G3 -> 2897370.5 | H4: =RECEITA!H3 -> 2897370.5 | I4: =RECEITA!I3 -> 2897370.5 | J4: =RECEITA!J3 -> 2897370.5 | K4: =RECEITA!K3 -> 2897370.5 | L4: =RECEITA!L3 -> 2897370.5 | ... Y4: =RECEITA!Y3 -> 2897370.5
B5: Receita biochar | C5: RECEITA | D5: -> RECEITA!4 | E5: =RECEITA!E4 -> 0 | F5: =RECEITA!F4 -> 0 | G5: =RECEITA!G4 -> 0 | H5: =RECEITA!H4 -> 0 | I5: =RECEITA!I4 -> 0 | J5: =RECEITA!J4 -> 0 | K5: =RECEITA!K4 -> 0 | L5: =RECEITA!L4 -> 0 | ... Y5: =RECEITA!Y4 -> 0
B6: Receita bruta total | C6: Calculado | D6: 4+5 | E6: =E4+E5 -> 0 | F6: =F4+F5 -> 2897370.5 | G6: =G4+G5 -> 2897370.5 | H6: =H4+H5 -> 2897370.5 | I6: =I4+I5 -> 2897370.5 | J6: =J4+J5 -> 2897370.5 | K6: =K4+K5 -> 2897370.5 | L6: =L4+L5 -> 2897370.5 | ... Y6: =Y4+Y5 -> 2897370.5
B7: PIS bruto - biochar | C7: PREMISSAS | D7: biochar x aliquota | E7: =E5*PREMISSAS!$C$111 -> 0 | F7: =F5*PREMISSAS!$C$111 -> 0 | G7: =G5*PREMISSAS!$C$111 -> 0 | H7: =H5*PREMISSAS!$C$111 -> 0 | I7: =I5*PREMISSAS!$C$111 -> 0 | J7: =J5*PREMISSAS!$C$111 -> 0 | K7: =K5*PREMISSAS!$C$111 -> 0 | L7: =L5*PREMISSAS!$C$111 -> 0 | ... Y7: =Y5*PREMISSAS!$C$111 -> 0
B8: COFINS bruto - biochar | C8: PREMISSAS | D8: biochar x aliquota | E8: =E5*PREMISSAS!$C$112 -> 0 | F8: =F5*PREMISSAS!$C$112 -> 0 | G8: =G5*PREMISSAS!$C$112 -> 0 | H8: =H5*PREMISSAS!$C$112 -> 0 | I8: =I5*PREMISSAS!$C$112 -> 0 | J8: =J5*PREMISSAS!$C$112 -> 0 | K8: =K5*PREMISSAS!$C$112 -> 0 | L8: =L5*PREMISSAS!$C$112 -> 0 | ... Y8: =Y5*PREMISSAS!$C$112 -> 0
B9: Base estimada de credito PIS/COFINS | C9: PREMISSAS | D9: OPEX caixa x fracao elegivel | E9: 0 | F9: =IF(OPEX!F22>0,OPEX!F22*PREMISSAS!$C$113,0) -> 0 | G9: =IF(OPEX!G22>0,OPEX!G22*PREMISSAS!$C$113,0) -> 0 | H9: =IF(OPEX!H22>0,OPEX!H22*PREMISSAS!$C$113,0) -> 0 | I9: =IF(OPEX!I22>0,OPEX!I22*PREMISSAS!$C$113,0) -> 0 | J9: =IF(OPEX!J22>0,OPEX!J22*PREMISSAS!$C$113,0) -> 0 | K9: =IF(OPEX!K22>0,OPEX!K22*PREMISSAS!$C$113,0) -> 0 | L9: =IF(OPEX!L22>0,OPEX!L22*PREMISSAS!$C$113,0) -> 0 | M9: =IF(OPEX!M22>0,OPEX!M22*PREMISSAS!$C$113,0) -> 0 | ... Y9: =IF(OPEX!Y22>0,OPEX!Y22*PREMISSAS!$C$113,0) -> 0
B10: Credito PIS estimado | C10: Calculado | D10: 9 x aliquota PIS | E10: =E9*PREMISSAS!$C$111 -> 0 | F10: =F9*PREMISSAS!$C$111 -> 0 | G10: =G9*PREMISSAS!$C$111 -> 0 | H10: =H9*PREMISSAS!$C$111 -> 0 | I10: =I9*PREMISSAS!$C$111 -> 0 | J10: =J9*PREMISSAS!$C$111 -> 0 | K10: =K9*PREMISSAS!$C$111 -> 0 | L10: =L9*PREMISSAS!$C$111 -> 0 | ... Y10: =Y9*PREMISSAS!$C$111 -> 0
B11: Credito COFINS estimado | C11: Calculado | D11: 9 x aliquota COFINS | E11: =E9*PREMISSAS!$C$112 -> 0 | F11: =F9*PREMISSAS!$C$112 -> 0 | G11: =G9*PREMISSAS!$C$112 -> 0 | H11: =H9*PREMISSAS!$C$112 -> 0 | I11: =I9*PREMISSAS!$C$112 -> 0 | J11: =J9*PREMISSAS!$C$112 -> 0 | K11: =K9*PREMISSAS!$C$112 -> 0 | L11: =L9*PREMISSAS!$C$112 -> 0 | ... Y11: =Y9*PREMISSAS!$C$112 -> 0
B12: PIS/COFINS líquidos (biochar + carbono) | C12: max(7+8-10-11,0) + carbono(4×alíquota) | D12: max(7+8-10-11,0) | E12: =MAX(E7+E8-E10-E11,0)+E4*(PREMISSAS!$C$109+PREMISSAS!$C$110) -> 0 | F12: =MAX(F7+F8-F10-F11,0)+F4*(PREMISSAS!$C$109+PREMISSAS!$C$110) -> 268006.77 | G12: =MAX(G7+G8-G10-G11,0)+G4*(PREMISSAS!$C$109+PREMISSAS!$C$110) -> 268006.77 | H12: =MAX(H7+H8-H10-H11,0)+H4*(PREMISSAS!$C$109+PREMISSAS!$C$110) -> 268006.77 | I12: =MAX(I7+I8-I10-I11,0)+I4*(PREMISSAS!$C$109+PREMISSAS!$C$110) -> 268006.77 | J12: =MAX(J7+J8-J10-J11,0)+J4*(PREMISSAS!$C$109+PREMISSAS!$C$110) -> 268006.77 | K12: =MAX(K7+K8-K10-K11,0)+K4*(PREMISSAS!$C$109+PREMISSAS!$C$110) -> 268006.77 | L12: =MAX(L7+L8-L10-L11,0)+L4*(PREMISSAS!$C$109+PREMISSAS!$C$110) -> 268006.77 | ... Y12: =MAX(Y7+Y8-Y10-Y11,0)+Y4*(PREMISSAS!$C$109+PREMISSAS!$C$110) -> 268006.77
B13: Lucro antes de IRPJ/CSLL | C13: DRE_FCL | D13: equivale ao EBIT no modelo atual | E13: =DRE_FCL!E11 -> 0 | F13: =DRE_FCL!F11 -> 939734.97 | G13: =DRE_FCL!G11 -> 917634.97 | H13: =DRE_FCL!H11 -> 895534.97 | I13: =DRE_FCL!I11 -> 873434.97 | J13: =DRE_FCL!J11 -> 851334.97 | K13: =DRE_FCL!K11 -> 829234.97 | L13: =DRE_FCL!L11 -> 807134.97 | ... Y13: =DRE_FCL!Y11 -> 740834.97
B14: Adicoes fiscais | C14: PREMISSAS | D14: ajuste manual | E14: =PREMISSAS!$C$120 -> 0 | F14: =PREMISSAS!$C$120 -> 0 | G14: =PREMISSAS!$C$120 -> 0 | H14: =PREMISSAS!$C$120 -> 0 | I14: =PREMISSAS!$C$120 -> 0 | J14: =PREMISSAS!$C$120 -> 0 | K14: =PREMISSAS!$C$120 -> 0 | L14: =PREMISSAS!$C$120 -> 0 | ... Y14: =PREMISSAS!$C$120 -> 0
B15: Exclusoes fiscais | C15: PREMISSAS | D15: ajuste manual | E15: =PREMISSAS!$C$121 -> 0 | F15: =PREMISSAS!$C$121 -> 0 | G15: =PREMISSAS!$C$121 -> 0 | H15: =PREMISSAS!$C$121 -> 0 | I15: =PREMISSAS!$C$121 -> 0 | J15: =PREMISSAS!$C$121 -> 0 | K15: =PREMISSAS!$C$121 -> 0 | L15: =PREMISSAS!$C$121 -> 0 | ... Y15: =PREMISSAS!$C$121 -> 0
B16: Lucro real antes compensacoes | C16: Calculado | D16: 13+14-15 | E16: =E13+E14-E15 -> 0 | F16: =F13+F14-F15 -> 939734.97 | G16: =G13+G14-G15 -> 917634.97 | H16: =H13+H14-H15 -> 895534.97 | I16: =I13+I14-I15 -> 873434.97 | J16: =J13+J14-J15 -> 851334.97 | K16: =K13+K14-K15 -> 829234.97 | L16: =L13+L14-L15 -> 807134.97 | ... Y16: =Y13+Y14-Y15 -> 740834.97
B17: Prejuizo fiscal acumulado inicial | C17: Calculado | D17: saldo do ano anterior | E17: 0 | F17: =E26 -> 0 | G17: =F26 -> 0 | H17: =G26 -> 0 | I17: =H26 -> 0 | J17: =I26 -> 0 | K17: =J26 -> 0 | L17: =K26 -> 0 | M17: =L26 -> 0 | ... Y17: =X26 -> 0
B18: Compensacao de prejuizo fiscal | C18: Calculado | D18: limitada a 30% | E18: =IF(E16>0,MIN(E17,E16*PREMISSAS!$C$118),0) -> 0 | F18: =IF(F16>0,MIN(F17,F16*PREMISSAS!$C$118),0) -> 0 | G18: =IF(G16>0,MIN(G17,G16*PREMISSAS!$C$118),0) -> 0 | H18: =IF(H16>0,MIN(H17,H16*PREMISSAS!$C$118),0) -> 0 | I18: =IF(I16>0,MIN(I17,I16*PREMISSAS!$C$118),0) -> 0 | J18: =IF(J16>0,MIN(J17,J16*PREMISSAS!$C$118),0) -> 0 | K18: =IF(K16>0,MIN(K17,K16*PREMISSAS!$C$118),0) -> 0 | L18: =IF(L16>0,MIN(L17,L16*PREMISSAS!$C$118),0) -> 0 | ... Y18: =IF(Y16>0,MIN(Y17,Y16*PREMISSAS!$C$118),0) -> 0
B19: Base IRPJ | C19: Calculado | D19: 16-18 | E19: =MAX(E16-E18,0) -> 0 | F19: =MAX(F16-F18,0) -> 939734.97 | G19: =MAX(G16-G18,0) -> 917634.97 | H19: =MAX(H16-H18,0) -> 895534.97 | I19: =MAX(I16-I18,0) -> 873434.97 | J19: =MAX(J16-J18,0) -> 851334.97 | K19: =MAX(K16-K18,0) -> 829234.97 | L19: =MAX(L16-L18,0) -> 807134.97 | ... Y19: =MAX(Y16-Y18,0) -> 740834.97
B20: IRPJ 15% | C20: Calculado | D20: 19 x aliquota | E20: =E19*PREMISSAS!$C$114 -> 0 | F20: =F19*PREMISSAS!$C$114 -> 140960.25 | G20: =G19*PREMISSAS!$C$114 -> 137645.25 | H20: =H19*PREMISSAS!$C$114 -> 134330.25 | I20: =I19*PREMISSAS!$C$114 -> 131015.25 | J20: =J19*PREMISSAS!$C$114 -> 127700.25 | K20: =K19*PREMISSAS!$C$114 -> 124385.25 | L20: =L19*PREMISSAS!$C$114 -> 121070.25 | ... Y20: =Y19*PREMISSAS!$C$114 -> 111125.25
B21: Adicional IRPJ 10% | C21: Calculado | D21: base acima do limite anual | E21: =MAX(E19-PREMISSAS!$C$116,0)*PREMISSAS!$C$115 -> 0 | F21: =MAX(F19-PREMISSAS!$C$116,0)*PREMISSAS!$C$115 -> 69973.497 | G21: =MAX(G19-PREMISSAS!$C$116,0)*PREMISSAS!$C$115 -> 67763.497 | H21: =MAX(H19-PREMISSAS!$C$116,0)*PREMISSAS!$C$115 -> 65553.497 | I21: =MAX(I19-PREMISSAS!$C$116,0)*PREMISSAS!$C$115 -> 63343.497 | J21: =MAX(J19-PREMISSAS!$C$116,0)*PREMISSAS!$C$115 -> 61133.497 | K21: =MAX(K19-PREMISSAS!$C$116,0)*PREMISSAS!$C$115 -> 58923.497 | L21: =MAX(L19-PREMISSAS!$C$116,0)*PREMISSAS!$C$115 -> 56713.497 | ... Y21: =MAX(Y19-PREMISSAS!$C$116,0)*PREMISSAS!$C$115 -> 50083.497
B22: Base negativa CSLL inicial | C22: Calculado | D22: saldo do ano anterior | E22: 0 | F22: =E27 -> 0 | G22: =F27 -> 0 | H22: =G27 -> 0 | I22: =H27 -> 0 | J22: =I27 -> 0 | K22: =J27 -> 0 | L22: =K27 -> 0 | M22: =L27 -> 0 | ... Y22: =X27 -> 0
B23: Compensacao base negativa CSLL | C23: Calculado | D23: limitada a 30% | E23: =IF(E16>0,MIN(E22,E16*PREMISSAS!$C$119),0) -> 0 | F23: =IF(F16>0,MIN(F22,F16*PREMISSAS!$C$119),0) -> 0 | G23: =IF(G16>0,MIN(G22,G16*PREMISSAS!$C$119),0) -> 0 | H23: =IF(H16>0,MIN(H22,H16*PREMISSAS!$C$119),0) -> 0 | I23: =IF(I16>0,MIN(I22,I16*PREMISSAS!$C$119),0) -> 0 | J23: =IF(J16>0,MIN(J22,J16*PREMISSAS!$C$119),0) -> 0 | K23: =IF(K16>0,MIN(K22,K16*PREMISSAS!$C$119),0) -> 0 | L23: =IF(L16>0,MIN(L22,L16*PREMISSAS!$C$119),0) -> 0 | ... Y23: =IF(Y16>0,MIN(Y22,Y16*PREMISSAS!$C$119),0) -> 0
B24: Base CSLL | C24: Calculado | D24: 16-23 | E24: =MAX(E16-E23,0) -> 0 | F24: =MAX(F16-F23,0) -> 939734.97 | G24: =MAX(G16-G23,0) -> 917634.97 | H24: =MAX(H16-H23,0) -> 895534.97 | I24: =MAX(I16-I23,0) -> 873434.97 | J24: =MAX(J16-J23,0) -> 851334.97 | K24: =MAX(K16-K23,0) -> 829234.97 | L24: =MAX(L16-L23,0) -> 807134.97 | ... Y24: =MAX(Y16-Y23,0) -> 740834.97
B25: CSLL 9% | C25: Calculado | D25: 24 x aliquota | E25: =E24*PREMISSAS!$C$117 -> 0 | F25: =F24*PREMISSAS!$C$117 -> 84576.148 | G25: =G24*PREMISSAS!$C$117 -> 82587.148 | H25: =H24*PREMISSAS!$C$117 -> 80598.148 | I25: =I24*PREMISSAS!$C$117 -> 78609.148 | J25: =J24*PREMISSAS!$C$117 -> 76620.148 | K25: =K24*PREMISSAS!$C$117 -> 74631.148 | L25: =L24*PREMISSAS!$C$117 -> 72642.148 | ... Y25: =Y24*PREMISSAS!$C$117 -> 66675.148
B26: Prejuizo fiscal acumulado final | C26: Calculado | D26: saldo para o proximo ano | E26: =MAX(E17-E18,0)+MAX(-E16,0) -> 0 | F26: =MAX(F17-F18,0)+MAX(-F16,0) -> 0 | G26: =MAX(G17-G18,0)+MAX(-G16,0) -> 0 | H26: =MAX(H17-H18,0)+MAX(-H16,0) -> 0 | I26: =MAX(I17-I18,0)+MAX(-I16,0) -> 0 | J26: =MAX(J17-J18,0)+MAX(-J16,0) -> 0 | K26: =MAX(K17-K18,0)+MAX(-K16,0) -> 0 | L26: =MAX(L17-L18,0)+MAX(-L16,0) -> 0 | ... Y26: =MAX(Y17-Y18,0)+MAX(-Y16,0) -> 0
B27: Base negativa CSLL final | C27: Calculado | D27: saldo para o proximo ano | E27: =MAX(E22-E23,0)+MAX(-E16,0) -> 0 | F27: =MAX(F22-F23,0)+MAX(-F16,0) -> 0 | G27: =MAX(G22-G23,0)+MAX(-G16,0) -> 0 | H27: =MAX(H22-H23,0)+MAX(-H16,0) -> 0 | I27: =MAX(I22-I23,0)+MAX(-I16,0) -> 0 | J27: =MAX(J22-J23,0)+MAX(-J16,0) -> 0 | K27: =MAX(K22-K23,0)+MAX(-K16,0) -> 0 | L27: =MAX(L22-L23,0)+MAX(-L16,0) -> 0 | ... Y27: =MAX(Y22-Y23,0)+MAX(-Y16,0) -> 0
B28: TRIBUTOS TOTAIS | C28: Calculado | D28: 12 + 20 + 21 + 25 | E28: =E12+E20+E21+E25 -> 0 | F28: =F12+F20+F21+F25 -> 563516.66 | G28: =G12+G20+G21+G25 -> 556002.66 | H28: =H12+H20+H21+H25 -> 548488.66 | I28: =I12+I20+I21+I25 -> 540974.66 | J28: =J12+J20+J21+J25 -> 533460.66 | K28: =K12+K20+K21+K25 -> 525946.66 | L28: =L12+L20+L21+L25 -> 518432.66 | ... Y28: =Y12+Y20+Y21+Y25 -> 495890.66
B29: Aliquota efetiva s/ receita bruta | C29: Calculado | D29: 28 / 6 | E29: =IF(E6<>0,E28/E6,0) -> 0 | F29: =IF(F6<>0,F28/F6,0) -> 0.19449244 | G29: =IF(G6<>0,G28/G6,0) -> 0.19189906 | H29: =IF(H6<>0,H28/H6,0) -> 0.18930567 | I29: =IF(I6<>0,I28/I6,0) -> 0.18671228 | J29: =IF(J6<>0,J28/J6,0) -> 0.1841189 | K29: =IF(K6<>0,K28/K6,0) -> 0.18152551 | L29: =IF(L6<>0,L28/L6,0) -> 0.17893213 | ... Y29: =IF(Y6<>0,Y28/Y6,0) -> 0.17115197

Sheet OPEX
B1: OPEX | Custos Operacionais por Driver
B2: Estrutura separada por motor economico: por tonelada processada, por mes de campanha e fixos anuais de existencia do projeto.
B3: Item de Custo | C3: Classe | D3: Motor Economico | E3: 2026 | F3: 2027 | G3: 2028 | H3: 2029 | I3: 2030 | J3: 2031 | K3: 2032 | L3: 2033 | M3: 2034 | N3: 2035 | O3: 2036 | P3: 2037 | Q3: 2038 | R3: 2039 | S3: 2040 | T3: 2041 | U3: 2042 | V3: 2043 | W3: 2044 | X3: 2045 | Y3: 2046
B4: CUSTOS POR TONELADA PROCESSADA
B5: Energia eletrica variavel - somente meses com operacao | C5: Por tonelada processada | D5: Consumo kWh de processo/startup x tarifa efetiva; meses sem operacao nao geram consumo do projeto | E5: =IF(CÁLCULO!E4>0,(((CÁLCULO!E4*PREMISSAS!$C$48)+PREMISSAS!$C$45)*PREMISSAS!$C$78),0) -> 0 | F5: =IF(CÁLCULO!F4>0,(((CÁLCULO!F4*PREMISSAS!$C$48)+PREMISSAS!$C$45)*PREMISSAS!$C$78),0) -> 624196.09 | G5: =IF(CÁLCULO!G4>0,(((CÁLCULO!G4*PREMISSAS!$C$48)+PREMISSAS!$C$45)*PREMISSAS!$C$78),0) -> 624196.09 | H5: =IF(CÁLCULO!H4>0,(((CÁLCULO!H4*PREMISSAS!$C$48)+PREMISSAS!$C$45)*PREMISSAS!$C$78),0) -> 624196.09 | I5: =IF(CÁLCULO!I4>0,(((CÁLCULO!I4*PREMISSAS!$C$48)+PREMISSAS!$C$45)*PREMISSAS!$C$78),0) -> 624196.09 | J5: =IF(CÁLCULO!J4>0,(((CÁLCULO!J4*PREMISSAS!$C$48)+PREMISSAS!$C$45)*PREMISSAS!$C$78),0) -> 624196.09 | K5: =IF(CÁLCULO!K4>0,(((CÁLCULO!K4*PREMISSAS!$C$48)+PREMISSAS!$C$45)*PREMISSAS!$C$78),0) -> 624196.09 | L5: =IF(CÁLCULO!L4>0,(((CÁLCULO!L4*PREMISSAS!$C$48)+PREMISSAS!$C$45)*PREMISSAS!$C$78),0) -> 624196.09 | ... Y5: =IF(CÁLCULO!Y4>0,(((CÁLCULO!Y4*PREMISSAS!$C$48)+PREMISSAS!$C$45)*PREMISSAS!$C$78),0) -> 624196.09
B6: Logistica de coleta | C6: Por tonelada processada | D6: R$/t biomassa | E6: 0 | F6: =PREMISSAS!$C$53*CÁLCULO!F4 -> 141870.33 | G6: =PREMISSAS!$C$53*CÁLCULO!G4 -> 141870.33 | H6: =PREMISSAS!$C$53*CÁLCULO!H4 -> 141870.33 | I6: =PREMISSAS!$C$53*CÁLCULO!I4 -> 141870.33 | J6: =PREMISSAS!$C$53*CÁLCULO!J4 -> 141870.33 | K6: =PREMISSAS!$C$53*CÁLCULO!K4 -> 141870.33 | L6: =PREMISSAS!$C$53*CÁLCULO!L4 -> 141870.33 | M6: =PREMISSAS!$C$53*CÁLCULO!M4 -> 141870.33 | ... Y6: =PREMISSAS!$C$53*CÁLCULO!Y4 -> 141870.33
B7: Logistica de transporte | C7: Por tonelada processada | D7: R$/t biomassa | E7: 0 | F7: =PREMISSAS!$C$54*CÁLCULO!F4 -> 236450.55 | G7: =PREMISSAS!$C$54*CÁLCULO!G4 -> 236450.55 | H7: =PREMISSAS!$C$54*CÁLCULO!H4 -> 236450.55 | I7: =PREMISSAS!$C$54*CÁLCULO!I4 -> 236450.55 | J7: =PREMISSAS!$C$54*CÁLCULO!J4 -> 236450.55 | K7: =PREMISSAS!$C$54*CÁLCULO!K4 -> 236450.55 | L7: =PREMISSAS!$C$54*CÁLCULO!L4 -> 236450.55 | M7: =PREMISSAS!$C$54*CÁLCULO!M4 -> 236450.55 | ... Y7: =PREMISSAS!$C$54*CÁLCULO!Y4 -> 236450.55
B8: Big bags e embalagem | C8: Por tonelada processada | D8: R$/t biochar | E8: 0 | F8: =PREMISSAS!$C$57*CÁLCULO!F5 -> 25264.741 | G8: =PREMISSAS!$C$57*CÁLCULO!G5 -> 25264.741 | H8: =PREMISSAS!$C$57*CÁLCULO!H5 -> 25264.741 | I8: =PREMISSAS!$C$57*CÁLCULO!I5 -> 25264.741 | J8: =PREMISSAS!$C$57*CÁLCULO!J5 -> 25264.741 | K8: =PREMISSAS!$C$57*CÁLCULO!K5 -> 25264.741 | L8: =PREMISSAS!$C$57*CÁLCULO!L5 -> 25264.741 | M8: =PREMISSAS!$C$57*CÁLCULO!M5 -> 25264.741 | ... Y8: =PREMISSAS!$C$57*CÁLCULO!Y5 -> 25264.741
B9: Material de laboratorio | C9: Por tonelada processada | D9: R$/t biochar | E9: 0 | F9: =PREMISSAS!$C$58*CÁLCULO!F5 -> 36094.177 | G9: =PREMISSAS!$C$58*CÁLCULO!G5 -> 36094.177 | H9: =PREMISSAS!$C$58*CÁLCULO!H5 -> 36094.177 | I9: =PREMISSAS!$C$58*CÁLCULO!I5 -> 36094.177 | J9: =PREMISSAS!$C$58*CÁLCULO!J5 -> 36094.177 | K9: =PREMISSAS!$C$58*CÁLCULO!K5 -> 36094.177 | L9: =PREMISSAS!$C$58*CÁLCULO!L5 -> 36094.177 | M9: =PREMISSAS!$C$58*CÁLCULO!M5 -> 36094.177 | ... Y9: =PREMISSAS!$C$58*CÁLCULO!Y5 -> 36094.177
B10: SUBTOTAL CUSTOS POR TONELADA | E10: 0 | F10: =SUM(F5:F9) -> 1063875.9 | G10: =SUM(G5:G9) -> 1063875.9 | H10: =SUM(H5:H9) -> 1063875.9 | I10: =SUM(I5:I9) -> 1063875.9 | J10: =SUM(J5:J9) -> 1063875.9 | K10: =SUM(K5:K9) -> 1063875.9 | L10: =SUM(L5:L9) -> 1063875.9 | M10: =SUM(M5:M9) -> 1063875.9 | ... Y10: =SUM(Y5:Y9) -> 1063875.9
B11: CUSTOS POR MES DE CAMPANHA
B12: Mao de obra operacional | C12: Por mes de campanha | D12: Operadores x salario x meses de calendario da campanha | E12: 0 | F12: =PREMISSAS!$C$51*PREMISSAS!$C$50*CÁLCULO!F10 -> 354675.83 | G12: =PREMISSAS!$C$51*PREMISSAS!$C$50*CÁLCULO!G10 -> 354675.83 | H12: =PREMISSAS!$C$51*PREMISSAS!$C$50*CÁLCULO!H10 -> 354675.83 | I12: =PREMISSAS!$C$51*PREMISSAS!$C$50*CÁLCULO!I10 -> 354675.83 | J12: =PREMISSAS!$C$51*PREMISSAS!$C$50*CÁLCULO!J10 -> 354675.83 | K12: =PREMISSAS!$C$51*PREMISSAS!$C$50*CÁLCULO!K10 -> 354675.83 | L12: =PREMISSAS!$C$51*PREMISSAS!$C$50*CÁLCULO!L10 -> 354675.83 | M12: =PREMISSAS!$C$51*PREMISSAS!$C$50*CÁLCULO!M10 -> 354675.83 | ... Y12: =PREMISSAS!$C$51*PREMISSAS!$C$50*CÁLCULO!Y10 -> 354675.83
B13: O&M reator BST-30 | C13: O&M progressivo | D13: Ano n = MIN(n,10) x taxa ano 1 x CAPEX do reator BST-30; n=1 em 2027. Sem prorrata por meses de campanha. | E13: 0 | F13: =IF(CÁLCULO!F4>0,PREMISSAS!$C$52*MIN(1,10)*CAPEX!$C$6,0) -> 22100 | G13: =IF(CÁLCULO!G4>0,PREMISSAS!$C$52*MIN(2,10)*CAPEX!$C$6,0) -> 44200 | H13: =IF(CÁLCULO!H4>0,PREMISSAS!$C$52*MIN(3,10)*CAPEX!$C$6,0) -> 66300 | I13: =IF(CÁLCULO!I4>0,PREMISSAS!$C$52*MIN(4,10)*CAPEX!$C$6,0) -> 88400 | J13: =IF(CÁLCULO!J4>0,PREMISSAS!$C$52*MIN(5,10)*CAPEX!$C$6,0) -> 110500 | K13: =IF(CÁLCULO!K4>0,PREMISSAS!$C$52*MIN(6,10)*CAPEX!$C$6,0) -> 132600 | L13: =IF(CÁLCULO!L4>0,PREMISSAS!$C$52*MIN(7,10)*CAPEX!$C$6,0) -> 154700 | M13: =IF(CÁLCULO!M4>0,PREMISSAS!$C$52*MIN(8,10)*CAPEX!$C$6,0) -> 176800 | N13: =IF(CÁLCULO!N4>0,PREMISSAS!$C$52*MIN(9,10)*CAPEX!$C$6,0) -> 198900 | O13: =IF(CÁLCULO!O4>0,PREMISSAS!$C$52*MIN(10,10)*CAPEX!$C$6,0) -> 221000 | P13: =IF(CÁLCULO!P4>0,PREMISSAS!$C$52*MIN(11,10)*CAPEX!$C$6,0) -> 221000 | Q13: =IF(CÁLCULO!Q4>0,PREMISSAS!$C$52*MIN(12,10)*CAPEX!$C$6,0) -> 221000 | R13: =IF(CÁLCULO!R4>0,PREMISSAS!$C$52*MIN(13,10)*CAPEX!$C$6,0) -> 221000 | S13: =IF(CÁLCULO!S4>0,PREMISSAS!$C$52*MIN(14,10)*CAPEX!$C$6,0) -> 221000 | T13: =IF(CÁLCULO!T4>0,PREMISSAS!$C$52*MIN(15,10)*CAPEX!$C$6,0) -> 221000 | U13: =IF(CÁLCULO!U4>0,PREMISSAS!$C$52*MIN(16,10)*CAPEX!$C$6,0) -> 221000 | V13: =IF(CÁLCULO!V4>0,PREMISSAS!$C$52*MIN(17,10)*CAPEX!$C$6,0) -> 221000 | W13: =IF(CÁLCULO!W4>0,PREMISSAS!$C$52*MIN(18,10)*CAPEX!$C$6,0) -> 221000 | X13: =IF(CÁLCULO!X4>0,PREMISSAS!$C$52*MIN(19,10)*CAPEX!$C$6,0) -> 221000 | Y13: =IF(CÁLCULO!Y4>0,PREMISSAS!$C$52*MIN(20,10)*CAPEX!$C$6,0) -> 221000
B14: SUBTOTAL CUSTOS POR MES DE CAMPANHA | E14: 0 | F14: =SUM(F12:F13) -> 376775.83 | G14: =SUM(G12:G13) -> 398875.83 | H14: =SUM(H12:H13) -> 420975.83 | I14: =SUM(I12:I13) -> 443075.83 | J14: =SUM(J12:J13) -> 465175.83 | K14: =SUM(K12:K13) -> 487275.83 | L14: =SUM(L12:L13) -> 509375.83 | M14: =SUM(M12:M13) -> 531475.83 | ... Y14: =SUM(Y12:Y13) -> 575675.83
B15: CUSTOS FIXOS ANUAIS DE EXISTENCIA
B16: Demanda contratada Cemig A4 Verde 360 kW - 12 meses | C16: Fixo anual | D16: Custo fixo do projeto: demanda unica contratada x 12 meses, inclusive meses sem operacao | E16: =IF(CÁLCULO!E4>0,PREMISSAS!$C$79*PREMISSAS!$C$105,0) -> 0 | F16: =IF(CÁLCULO!F4>0,PREMISSAS!$C$79*PREMISSAS!$C$105,0) -> 129214.79 | G16: =IF(CÁLCULO!G4>0,PREMISSAS!$C$79*PREMISSAS!$C$105,0) -> 129214.79 | H16: =IF(CÁLCULO!H4>0,PREMISSAS!$C$79*PREMISSAS!$C$105,0) -> 129214.79 | I16: =IF(CÁLCULO!I4>0,PREMISSAS!$C$79*PREMISSAS!$C$105,0) -> 129214.79 | J16: =IF(CÁLCULO!J4>0,PREMISSAS!$C$79*PREMISSAS!$C$105,0) -> 129214.79 | K16: =IF(CÁLCULO!K4>0,PREMISSAS!$C$79*PREMISSAS!$C$105,0) -> 129214.79 | L16: =IF(CÁLCULO!L4>0,PREMISSAS!$C$79*PREMISSAS!$C$105,0) -> 129214.79 | ... Y16: =IF(CÁLCULO!Y4>0,PREMISSAS!$C$79*PREMISSAS!$C$105,0) -> 129214.79
B17: Auditoria e verificacao anual | C17: Fixo anual | D17: Obrigacao anual de conformidade / verificacao | E17: 0 | F17: =PREMISSAS!$C$55 -> 100000 | G17: =PREMISSAS!$C$55 -> 100000 | H17: =PREMISSAS!$C$55 -> 100000 | I17: =PREMISSAS!$C$55 -> 100000 | J17: =PREMISSAS!$C$55 -> 100000 | K17: =PREMISSAS!$C$55 -> 100000 | L17: =PREMISSAS!$C$55 -> 100000 | M17: =PREMISSAS!$C$55 -> 100000 | ... Y17: =PREMISSAS!$C$55 -> 100000
B18: Renovacao LCA + relatorio | C18: Fixo anual | D18: Obrigacao anual de conformidade / relatorio | E18: 0 | F18: =PREMISSAS!$C$56 -> 35000 | G18: =PREMISSAS!$C$56 -> 35000 | H18: =PREMISSAS!$C$56 -> 35000 | I18: =PREMISSAS!$C$56 -> 35000 | J18: =PREMISSAS!$C$56 -> 35000 | K18: =PREMISSAS!$C$56 -> 35000 | L18: =PREMISSAS!$C$56 -> 35000 | M18: =PREMISSAS!$C$56 -> 35000 | ... Y18: =PREMISSAS!$C$56 -> 35000
B19: Treinamento e outros fixos | C19: Fixo anual | D19: Custo recorrente de existencia do projeto | E19: 0 | F19: =PREMISSAS!$C$59 -> 10000 | G19: =PREMISSAS!$C$59 -> 10000 | H19: =PREMISSAS!$C$59 -> 10000 | I19: =PREMISSAS!$C$59 -> 10000 | J19: =PREMISSAS!$C$59 -> 10000 | K19: =PREMISSAS!$C$59 -> 10000 | L19: =PREMISSAS!$C$59 -> 10000 | M19: =PREMISSAS!$C$59 -> 10000 | ... Y19: =PREMISSAS!$C$59 -> 10000
B20: Diesel startup | C20: Por ciclo (variável com biomassa) | D20: Ciclos/ano × L/ciclo × R$/L via PREMISSAS!C96=C27×C94×C95. Escala com biomassa através de C27 (ciclos/ano). Classificado aqui por conveniência; motor econômico é variável com operação. | E20: 0 | F20: =PREMISSAS!$C$82 -> 19669 | G20: =PREMISSAS!$C$82 -> 19669 | H20: =PREMISSAS!$C$82 -> 19669 | I20: =PREMISSAS!$C$82 -> 19669 | J20: =PREMISSAS!$C$82 -> 19669 | K20: =PREMISSAS!$C$82 -> 19669 | L20: =PREMISSAS!$C$82 -> 19669 | M20: =PREMISSAS!$C$82 -> 19669 | ... Y20: =PREMISSAS!$C$82 -> 19669
B21: SUBTOTAL FIXOS ANUAIS | E21: 0 | F21: =SUM(F16:F20) -> 293883.79 | G21: =SUM(G16:G20) -> 293883.79 | H21: =SUM(H16:H20) -> 293883.79 | I21: =SUM(I16:I20) -> 293883.79 | J21: =SUM(J16:J20) -> 293883.79 | K21: =SUM(K16:K20) -> 293883.79 | L21: =SUM(L16:L20) -> 293883.79 | M21: =SUM(M16:M20) -> 293883.79 | ... Y21: =SUM(Y16:Y20) -> 293883.79
B22: TOTAL OPEX ANUAL | E22: 0 | F22: =F10+F14+F21 -> 1734535.5 | G22: =G10+G14+G21 -> 1756635.5 | H22: =H10+H14+H21 -> 1778735.5 | I22: =I10+I14+I21 -> 1800835.5 | J22: =J10+J14+J21 -> 1822935.5 | K22: =K10+K14+K21 -> 1845035.5 | L22: =L10+L14+L21 -> 1867135.5 | M22: =M10+M14+M21 -> 1889235.5 | ... Y22: =Y10+Y14+Y21 -> 1933435.5
B25: Tabela O&M progressivo do reator BST-30
B26: Ano | C26: Ano operacional | D26: Taxa O&M | E26: Base de c?lculo | F26: Valor O&M (R$) | G26: Regra aplicada
B27: 2027 | C27: 1 | D27: =MIN(C27,10)*PREMISSAS!$C$52 -> 0.01 | E27: =CAPEX!$C$6 -> 2210000 | F27: =OPEX!F$13 -> 22100 | G27: =TEXT(D27,"0%")&" x CAPEX do reator" -> 1% x CAPEX do reator
B28: 2028 | C28: 2 | D28: =MIN(C28,10)*PREMISSAS!$C$52 -> 0.02 | E28: =CAPEX!$C$6 -> 2210000 | F28: =OPEX!G$13 -> 44200 | G28: =TEXT(D28,"0%")&" x CAPEX do reator" -> 2% x CAPEX do reator
B29: 2029 | C29: 3 | D29: =MIN(C29,10)*PREMISSAS!$C$52 -> 0.03 | E29: =CAPEX!$C$6 -> 2210000 | F29: =OPEX!H$13 -> 66300 | G29: =TEXT(D29,"0%")&" x CAPEX do reator" -> 3% x CAPEX do reator
B30: 2030 | C30: 4 | D30: =MIN(C30,10)*PREMISSAS!$C$52 -> 0.04 | E30: =CAPEX!$C$6 -> 2210000 | F30: =OPEX!I$13 -> 88400 | G30: =TEXT(D30,"0%")&" x CAPEX do reator" -> 4% x CAPEX do reator
B31: 2031 | C31: 5 | D31: =MIN(C31,10)*PREMISSAS!$C$52 -> 0.05 | E31: =CAPEX!$C$6 -> 2210000 | F31: =OPEX!J$13 -> 110500 | G31: =TEXT(D31,"0%")&" x CAPEX do reator" -> 5% x CAPEX do reator
B32: 2032 | C32: 6 | D32: =MIN(C32,10)*PREMISSAS!$C$52 -> 0.06 | E32: =CAPEX!$C$6 -> 2210000 | F32: =OPEX!K$13 -> 132600 | G32: =TEXT(D32,"0%")&" x CAPEX do reator" -> 6% x CAPEX do reator
B33: 2033 | C33: 7 | D33: =MIN(C33,10)*PREMISSAS!$C$52 -> 0.07 | E33: =CAPEX!$C$6 -> 2210000 | F33: =OPEX!L$13 -> 154700 | G33: =TEXT(D33,"0%")&" x CAPEX do reator" -> 7% x CAPEX do reator
B34: 2034 | C34: 8 | D34: =MIN(C34,10)*PREMISSAS!$C$52 -> 0.08 | E34: =CAPEX!$C$6 -> 2210000 | F34: =OPEX!M$13 -> 176800 | G34: =TEXT(D34,"0%")&" x CAPEX do reator" -> 8% x CAPEX do reator
B35: 2035 | C35: 9 | D35: =MIN(C35,10)*PREMISSAS!$C$52 -> 0.09 | E35: =CAPEX!$C$6 -> 2210000 | F35: =OPEX!N$13 -> 198900 | G35: =TEXT(D35,"0%")&" x CAPEX do reator" -> 9% x CAPEX do reator
B36: 2036 | C36: 10 | D36: =MIN(C36,10)*PREMISSAS!$C$52 -> 0.1 | E36: =CAPEX!$C$6 -> 2210000 | F36: =OPEX!O$13 -> 221000 | G36: =TEXT(D36,"0%")&" x CAPEX do reator" -> 10% x CAPEX do reator
B37: 2037 | C37: 11 | D37: =MIN(C37,10)*PREMISSAS!$C$52 -> 0.1 | E37: =CAPEX!$C$6 -> 2210000 | F37: =OPEX!P$13 -> 221000 | G37: =TEXT(D37,"0%")&" x CAPEX do reator" -> 10% x CAPEX do reator
B38: 2038 | C38: 12 | D38: =MIN(C38,10)*PREMISSAS!$C$52 -> 0.1 | E38: =CAPEX!$C$6 -> 2210000 | F38: =OPEX!Q$13 -> 221000 | G38: =TEXT(D38,"0%")&" x CAPEX do reator" -> 10% x CAPEX do reator
B39: 2039 | C39: 13 | D39: =MIN(C39,10)*PREMISSAS!$C$52 -> 0.1 | E39: =CAPEX!$C$6 -> 2210000 | F39: =OPEX!R$13 -> 221000 | G39: =TEXT(D39,"0%")&" x CAPEX do reator" -> 10% x CAPEX do reator
B40: 2040 | C40: 14 | D40: =MIN(C40,10)*PREMISSAS!$C$52 -> 0.1 | E40: =CAPEX!$C$6 -> 2210000 | F40: =OPEX!S$13 -> 221000 | G40: =TEXT(D40,"0%")&" x CAPEX do reator" -> 10% x CAPEX do reator
B41: 2041 | C41: 15 | D41: =MIN(C41,10)*PREMISSAS!$C$52 -> 0.1 | E41: =CAPEX!$C$6 -> 2210000 | F41: =OPEX!T$13 -> 221000 | G41: =TEXT(D41,"0%")&" x CAPEX do reator" -> 10% x CAPEX do reator
B42: 2042 | C42: 16 | D42: =MIN(C42,10)*PREMISSAS!$C$52 -> 0.1 | E42: =CAPEX!$C$6 -> 2210000 | F42: =OPEX!U$13 -> 221000 | G42: =TEXT(D42,"0%")&" x CAPEX do reator" -> 10% x CAPEX do reator
B43: 2043 | C43: 17 | D43: =MIN(C43,10)*PREMISSAS!$C$52 -> 0.1 | E43: =CAPEX!$C$6 -> 2210000 | F43: =OPEX!V$13 -> 221000 | G43: =TEXT(D43,"0%")&" x CAPEX do reator" -> 10% x CAPEX do reator
B44: 2044 | C44: 18 | D44: =MIN(C44,10)*PREMISSAS!$C$52 -> 0.1 | E44: =CAPEX!$C$6 -> 2210000 | F44: =OPEX!W$13 -> 221000 | G44: =TEXT(D44,"0%")&" x CAPEX do reator" -> 10% x CAPEX do reator
B45: 2045 | C45: 19 | D45: =MIN(C45,10)*PREMISSAS!$C$52 -> 0.1 | E45: =CAPEX!$C$6 -> 2210000 | F45: =OPEX!X$13 -> 221000 | G45: =TEXT(D45,"0%")&" x CAPEX do reator" -> 10% x CAPEX do reator
B46: 2046 | C46: 20 | D46: =MIN(C46,10)*PREMISSAS!$C$52 -> 0.1 | E46: =CAPEX!$C$6 -> 2210000 | F46: =OPEX!Y$13 -> 221000 | G46: =TEXT(D46,"0%")&" x CAPEX do reator" -> 10% x CAPEX do reator
B48: Nota: o percentual de O&M incide sobre o CAPEX do reator BST-30 (CAPEX!C6), n?o sobre o CAPEX f?sico total. A partir do ano operacional 10, a taxa fica limitada a 10% ao ano.

Sheet DRE_FCL
B1: DRE SIMPLIFICADA + FLUXO DE CAIXA LIVRE
B2: Estrutura auditavel: cada linha referencia aba-fonte; tributos detalhados na aba TRIBUTOS.
B3: Item | C3: Origem | D3: Referência | E3: 2026 | F3: 2027 | G3: 2028 | H3: 2029 | I3: 2030 | J3: 2031 | K3: 2032 | L3: 2033 | M3: 2034 | N3: 2035 | O3: 2036 | P3: 2037 | Q3: 2038 | R3: 2039 | S3: 2040 | T3: 2041 | U3: 2042 | V3: 2043 | W3: 2044 | X3: 2045 | Y3: 2046
B4: (–) CAPEX — Investimento inicial | C4: CAPEX | D4: CAPEX!$C$15 | E4: =-CAPEX!$C$16 -> -5498000 | F4: 0 | G4: 0 | H4: 0 | I4: 0 | J4: 0 | K4: 0 | L4: 0 | M4: 0 | N4: 0 | O4: 0 | P4: 0 | Q4: 0 | R4: 0 | S4: 0 | T4: 0 | U4: 0 | V4: 0 | W4: 0 | X4: 0 | Y4: 0
B5: (+) Receita bruta total | C5: RECEITA | D5: → RECEITA!5 | E5: 0 | F5: =RECEITA!F5 -> 2897370.5 | G5: =RECEITA!G5 -> 2897370.5 | H5: =RECEITA!H5 -> 2897370.5 | I5: =RECEITA!I5 -> 2897370.5 | J5: =RECEITA!J5 -> 2897370.5 | K5: =RECEITA!K5 -> 2897370.5 | L5: =RECEITA!L5 -> 2897370.5 | M5: =RECEITA!M5 -> 2897370.5 | ... Y5: =RECEITA!Y5 -> 2897370.5
B6: (–) Fee Astra Carbon | C6: RECEITA | D6: → RECEITA!6 | E6: 0 | F6: =RECEITA!F6 -> 0 | G6: =RECEITA!G6 -> 0 | H6: =RECEITA!H6 -> 0 | I6: =RECEITA!I6 -> 0 | J6: =RECEITA!J6 -> 0 | K6: =RECEITA!K6 -> 0 | L6: =RECEITA!L6 -> 0 | M6: =RECEITA!M6 -> 0 | ... Y6: =RECEITA!Y6 -> 0
B7: (–) Total OPEX | C7: OPEX | D7: OPEX!22 | E7: 0 | F7: =-OPEX!F22 -> -1734535.5 | G7: =-OPEX!G22 -> -1756635.5 | H7: =-OPEX!H22 -> -1778735.5 | I7: =-OPEX!I22 -> -1800835.5 | J7: =-OPEX!J22 -> -1822935.5 | K7: =-OPEX!K22 -> -1845035.5 | L7: =-OPEX!L22 -> -1867135.5 | M7: =-OPEX!M22 -> -1889235.5 | ... Y7: =-OPEX!Y22 -> -1933435.5
B8: EBITDA | C8: Calculado | D8: bruta+astra+opex | E8: 0 | F8: =F5+F6+F7 -> 1162835 | G8: =G5+G6+G7 -> 1140735 | H8: =H5+H6+H7 -> 1118635 | I8: =I5+I6+I7 -> 1096535 | J8: =J5+J6+J7 -> 1074435 | K8: =K5+K6+K7 -> 1052335 | L8: =L5+L6+L7 -> 1030235 | M8: =M5+M6+M7 -> 1008135 | ... Y8: =Y5+Y6+Y7 -> 963934.97
B9: Margem EBITDA (%) | D9: EBITDA/Receita | E9: 0 | F9: =IF(F5<>0,F8/F5,0) -> 0.40134149 | G9: =IF(G5<>0,G8/G5,0) -> 0.39371388 | H9: =IF(H5<>0,H8/H5,0) -> 0.38608627 | I9: =IF(I5<>0,I8/I5,0) -> 0.37845867 | J9: =IF(J5<>0,J8/J5,0) -> 0.37083106 | K9: =IF(K5<>0,K8/K5,0) -> 0.36320346 | L9: =IF(L5<>0,L8/L5,0) -> 0.35557585 | M9: =IF(M5<>0,M8/M5,0) -> 0.34794824 | ... Y9: =IF(Y5<>0,Y8/Y5,0) -> 0.33269303
B10: (–) Depreciação | C10: CAPEX | D10: → CAPEX!23 | E10: =-CAPEX!E24 -> 0 | F10: =-CAPEX!F24 -> -223100 | G10: =-CAPEX!G24 -> -223100 | H10: =-CAPEX!H24 -> -223100 | I10: =-CAPEX!I24 -> -223100 | J10: =-CAPEX!J24 -> -223100 | K10: =-CAPEX!K24 -> -223100 | L10: =-CAPEX!L24 -> -223100 | ... Y10: =-CAPEX!Y24 -> -223100
B11: EBIT | C11: Calculado | D11: EBITDA−D&A | E11: 0 | F11: =F8+F10 -> 939734.97 | G11: =G8+G10 -> 917634.97 | H11: =H8+H10 -> 895534.97 | I11: =I8+I10 -> 873434.97 | J11: =J8+J10 -> 851334.97 | K11: =K8+K10 -> 829234.97 | L11: =L8+L10 -> 807134.97 | M11: =M8+M10 -> 785034.97 | ... Y11: =Y8+Y10 -> 740834.97
B12: (-) Tributos (PIS/COFINS + IRPJ/CSLL) | C12: TRIBUTOS | D12: -> TRIBUTOS!28 | E12: =-TRIBUTAÇÃO!E28 -> 0 | F12: =-TRIBUTAÇÃO!F28 -> -563516.66 | G12: =-TRIBUTAÇÃO!G28 -> -556002.66 | H12: =-TRIBUTAÇÃO!H28 -> -548488.66 | I12: =-TRIBUTAÇÃO!I28 -> -540974.66 | J12: =-TRIBUTAÇÃO!J28 -> -533460.66 | K12: =-TRIBUTAÇÃO!K28 -> -525946.66 | L12: =-TRIBUTAÇÃO!L28 -> -518432.66 | ... Y12: =-TRIBUTAÇÃO!Y28 -> -495890.66
B13: Lucro Líquido | C13: Calculado | D13: EBIT−IR | E13: 0 | F13: =F11+F12 -> 376218.31 | G13: =G11+G12 -> 361632.31 | H13: =H11+H12 -> 347046.31 | I13: =I11+I12 -> 332460.31 | J13: =J11+J12 -> 317874.31 | K13: =K11+K12 -> 303288.31 | L13: =L11+L12 -> 288702.31 | M13: =M11+M12 -> 274116.31 | ... Y13: =Y11+Y12 -> 244944.31
B14: (+) Add-back depreciação | C14: Não caixa | D14: reverso D&A | E14: 0 | F14: =-F10 -> 223100 | G14: =-G10 -> 223100 | H14: =-H10 -> 223100 | I14: =-I10 -> 223100 | J14: =-J10 -> 223100 | K14: =-K10 -> 223100 | L14: =-L10 -> 223100 | M14: =-M10 -> 223100 | ... Y14: =-Y10 -> 223100
B15: FCL — FLUXO DE CAIXA LIVRE | C15: Calculado | D15: CAPEX+LL+D&A | E15: =E4+E13+E14 -> -5498000 | F15: =F4+F13+F14 -> 599318.31 | G15: =G4+G13+G14 -> 584732.31 | H15: =H4+H13+H14 -> 570146.31 | I15: =I4+I13+I14 -> 555560.31 | J15: =J4+J13+J14 -> 540974.31 | K15: =K4+K13+K14 -> 526388.31 | L15: =L4+L13+L14 -> 511802.31 | ... Y15: =Y4+Y13+Y14 -> 468044.31
B16: FCL Acumulado | D16: running sum | E16: =E15 -> -5498000 | F16: =E16+F15 -> -4898681.7 | G16: =F16+G15 -> -4313949.4 | H16: =G16+H15 -> -3743803.1 | I16: =H16+I15 -> -3188242.7 | J16: =I16+J15 -> -2647268.4 | K16: =J16+K15 -> -2120880.1 | L16: =K16+L15 -> -1609077.8 | M16: =L16+M15 -> -1111861.5 | ... Y16: =X16+Y15 -> 4519256.3
B17: Delta Capital de Giro | C17: WC recebíveis | D17: prazo×rec/12 | E17: =IF(PREMISSAS!$C$107=1,-(RECEITA!F5/12)*PREMISSAS!$C$106,0) -> 0 | F17: 0 | G17: 0 | H17: 0 | I17: 0 | J17: 0 | K17: 0 | L17: 0 | M17: 0 | N17: 0 | O17: 0 | P17: 0 | Q17: 0 | R17: 0 | S17: 0 | T17: 0 | U17: 0 | V17: 0 | W17: 0 | X17: 0 | Y17: =IF(PREMISSAS!$C$107=1,(RECEITA!F5/12)*PREMISSAS!$C$106,0) -> 0
B18: FCL incluindo Capital de Giro | C18: Calculado | D18: FCL+Delta WC | E18: =E15+E17 -> -5498000 | F18: =F15+F17 -> 599318.31 | G18: =G15+G17 -> 584732.31 | H18: =H15+H17 -> 570146.31 | I18: =I15+I17 -> 555560.31 | J18: =J15+J17 -> 540974.31 | K18: =K15+K17 -> 526388.31 | L18: =L15+L17 -> 511802.31 | ... Y18: =Y15+Y17 -> 468044.31
B19: FCL Acumulado c/ Capital de Giro | D19: running sum | E19: =E18 -> -5498000 | F19: =E19+F18 -> -4898681.7 | G19: =F19+G18 -> -4313949.4 | H19: =G19+H18 -> -3743803.1 | I19: =H19+I18 -> -3188242.7 | J19: =I19+J18 -> -2647268.4 | K19: =J19+K18 -> -2120880.1 | L19: =K19+L18 -> -1609077.8 | M19: =L19+M18 -> -1111861.5 | ... Y19: =X19+Y18 -> 4519256.3

Sheet ENERGIA
B1: ENERGIA | C1: Caso-base eletrico unico: Cemig A4 Verde 360 kW, cominuicao fora ponta e gestao ativa de demanda | D1: Caso-base eletrico: Cemig A4 Verde 360 kW; cominuicao fora ponta; pirolise 24h
B2: Indicadores consolidados do cenario base. Consumo = potencia x fator de utilizacao.
B5: Base Operacional
B6: Modalidade eletrica base | C6: =PREMISSAS!$C$47 -> Cemig A4 Verde 360 kW | D6: contrato
B7: Biomassa processada (ano base) | C7: =CÁLCULO!F4 -> 3940.8425 | D7: t/ano
B8: Dias de operacao/ano | C8: =CÁLCULO!F9 -> 164.20177 | D8: dias/ano
B9: Meses de calendario/ano | C9: =CÁLCULO!F10 -> 6.5680709 | D9: meses/ano
B10: Demanda contratada Cemig | C10: =PREMISSAS!$C$62 -> 360 | D10: kW
B11: Pico kW cominuicao completa | C11: 191.5 | D11: kW
B12: Pico kW pirolise | C12: 178.95 | D12: kW
B13: Pico tecnico sem gestao | C13: 370.45 | D13: kW
B15: kWh/t Fase 1 - pre-processamento | C15: 41.125 | D15: kWh/t
B16: kWh/t Fase 2 - reator | C16: 166.25 | D16: kWh/t
B17: kWh/t startup overhead | C17: =IF(C7>0,PREMISSAS!$C$45/C7,0) -> 0.5176558 | D17: kWh/t
B18: kWh/t all-in caso-base | C18: =C15+C16+C17 -> 207.89266 | D18: kWh/t
B20: Indicadores de Custo
B21: Tarifa efetiva consumo A4 Verde | C21: =PREMISSAS!$C$78 -> 0.76189095 | D21: R$/kWh
B22: Custo variavel anual de energia | C22: =C45 -> 624196.09 | D22: R$/ano | E22: Ponta + fora ponta, com impostos
B23: Custo anual demanda contratada | C23: =IF(C7>0,PREMISSAS!$C$79*PREMISSAS!$C$105,0) -> 129214.79 | D23: R$/ano | E23: Demanda fixa 12 meses, inclusive meses sem operacao
B24: Custo energia eletrica total | C24: =C22+C23 -> 753410.88 | D24: R$/ano | E24: Consumo somente nos meses com operacao + demanda fixa anual
B25: R$/t variavel | C25: =IF(C7>0,C22/C7,0) -> 158.39153 | D25: R$/t
B26: R$/t energia eletrica | C26: =IF(C7>0,C24/C7,0) -> 191.18015 | D26: R$/t
B28: Memoria anual - kWh ponta/fora ponta e custo com impostos
B29: Consumo processo anual - cominuicao | C29: =C7*C15 -> 162067.15 | D29: kWh/ano | E29: Assume 6h/dia programadas fora de ponta
B30: Consumo processo anual - pirolise | C30: =C7*C16 -> 655165.07 | D30: kWh/ano | E30: Pirolise 24h/dia
B31: Startup eletrico anual | C31: =PREMISSAS!$C$45 -> 2040 | D31: kWh/ano | E31: Startup tratado como fora ponta no caso-base
B32: Consumo eletrico total all-in | C32: =SUM(C29:C31) -> 819272.22 | D32: kWh/ano
B34: kWh ponta - pirolise | C34: =C30*PREMISSAS!$C$76 -> 58496.881 | D34: kWh/ano | E34: Ponta media: 3h x 5/7 / 24; feriados nao descontados
B35: kWh ponta - cominuicao | C35: =C29*PREMISSAS!$C$77*PREMISSAS!$C$76 -> 0 | D35: kWh/ano | E35: Caso-base 0: cominuicao fora de ponta
B36: kWh ponta total | C36: =C34+C35 -> 58496.881 | D36: kWh/ano
B37: kWh fora ponta - pirolise | C37: =C30-C34 -> 596668.19 | D37: kWh/ano
B38: kWh fora ponta - cominuicao | C38: =C29-C35 -> 162067.15 | D38: kWh/ano
B39: kWh fora ponta - startup | C39: =C31 -> 2040 | D39: kWh/ano
B40: kWh fora ponta total | C40: =SUM(C37:C39) -> 760775.34 | D40: kWh/ano
B42: Custo consumo ponta | C42: =C36*PREMISSAS!$C$73 -> 175272.8 | D42: R$/ano | E42: Tarifa ponta com PIS/COFINS + ICMS
B43: Custo consumo fora ponta | C43: =C40*PREMISSAS!$C$74 -> 448923.29 | D43: R$/ano | E43: Tarifa fora ponta com PIS/COFINS + ICMS
B44: Custo consumo total | C44: =C42+C43 -> 624196.09 | D44: R$/ano
B45: Custo variavel usado no OPEX | C45: =C44 -> 624196.09 | D45: R$/ano
B46: Custo demanda 360 kW | C46: =IF(C7>0,PREMISSAS!$C$79*PREMISSAS!$C$105,0) -> 129214.79 | D46: R$/ano | E46: Demanda unica A4 Verde
B47: Energia eletrica total | C47: =C45+C46 -> 753410.88 | D47: R$/ano
B48: Diesel startup | C48: =PREMISSAS!$C$82 -> 19669 | D48: R$/ano | E48: Componente termico de partida
B49: Energia eletrica + diesel | C49: =C47+C48 -> 773079.88 | D49: R$/ano
B50: R$/t energia + diesel | C50: =IF(C7>0,C49/C7,0) -> 196.17122 | D50: R$/t
E54: Leitura tecnica | F54: Acao recomendada
E55: Contrato assinado | F55: Manter como base da obra e do OPEX.
E56: Referencia de alerta | F56: Confirmar criterio exato no contrato/fatura Cemig.
E57: Cominuicao completa + pirolise | F57: Nao e o caso-base financeiro; usar como alerta operacional.
E58: Com gestao ativa de demanda | F58: Operacao sequenciada para manter demanda medida <= 360 kW; nao e um cenario alternativo.
E59: Alerta automatico | F59: Caso-base deve permanecer dentro do contrato, nao apenas dentro da tolerancia.
E60: Margem tecnica | F60: Margem apertada; requer protocolo operacional e acompanhamento da memoria de massa.
B62: Alocacao anual: meses com operacao vs meses sem operacao
B63: Item | C63: Valor | D63: Unidade | E63: Tratamento no modelo | F63: Impacto financeiro
B64: Meses com operacao | C64: =C9 -> 6.5680709 | D64: meses/ano | E64: Derivado da biomassa disponivel e disponibilidade do reator | F64: Consumo eletrico de processo ocorre aqui
B65: Meses sem operacao | C65: =MAX(PREMISSAS!$C$105-C64,0) -> 5.4319291 | D65: meses/ano | E65: Meses restantes do ano sem processamento de biomassa | F65: Consumo eletrico operacional = zero
B66: Consumo eletrico nos meses com operacao | C66: =C44 -> 624196.09 | D66: R$/ano | E66: Custo variavel total ponta + fora ponta gerado pelo kWh operacional | F66: Entra no OPEX como energia variavel
B67: Consumo eletrico nos meses sem operacao | C67: =0 -> 0 | D67: R$/ano | E67: Sem processamento, sem consumo operacional alocado ao projeto | F67: Nao entra no OPEX
B68: Demanda fixa durante operacao | C68: =C46*C64/PREMISSAS!$C$105 -> 70724.326 | D68: R$/ano | E68: Parcela informativa da demanda anual durante meses de campanha | F68: Custo do projeto
B69: Demanda fixa sem operacao | C69: =C46*C65/PREMISSAS!$C$105 -> 58490.466 | D69: R$/ano | E69: Parcela informativa da demanda anual nos meses ociosos | F69: Continua custo do projeto
B70: Demanda fixa total | C70: =C68+C69 -> 129214.79 | D70: R$/ano | E70: 360 kW x 12 meses | F70: Entra integralmente no OPEX
B71: Energia eletrica total do projeto | C71: =C66+C67+C70 -> 753410.88 | D71: R$/ano | E71: Consumo apenas na operacao + demanda nos 12 meses | F71: Base do OPEX eletrico anual

Sheet ANALISE_CEMIG
B1: ANALISE CEMIG A4 VERDE - BCNE
B2: Caso-base combinado: demanda contratada 360 kW, A4 Verde, cominuicao fora ponta e gestao ativa de demanda para respeitar o contrato.
B4: Tema | C4: Base | D4: Conclusao / acao
B5: Fonte tarifaria | C5: Cemig Tarifas Vigentes / Res. Hom. ANEEL 3.459/2025 | D5: A4 Verde: demanda 22,81 R$/kW mes; consumo ponta 2,28496 R$/kWh; fora ponta 0,45 R$/kWh, antes de impostos.
B6: Impostos | C6: Cemig PIS/COFINS Mar/2026 + ICMS 18% | D6: PASEP 1,25%, COFINS 5,75%, fator gross-up ~1,3113. Atualizar mensalmente pela fatura.
B7: Horario de ponta | C7: Cemig | D7: 17h-20h em dias uteis. Fins de semana e feriados nacionais tratados como fora ponta; modelo usa media 5/7 e nao desconta feriados.
B8: Demanda contratada | C8: Contrato assinado | D8: 360 kW. Pico simultaneo estimado com cominuicao completa + pirolise fica acima de 360 kW, mas abaixo de 360 kW + 5% no caso-base.
B9: Gestao operacional | C9: Engenharia eletrica | D9: Programar cominuicao fora do horario de ponta. Evitar partida de crusher/fine crusher simultanea com transientes do reator/secador.
B10: Risco contratual | C10: Cemig media tensao | D10: Se memoria de massa registrar demanda acima do limite contratual/tolerancia, aplica tarifa de ultrapassagem. Confirmar criterio exato no contrato.
B11: Rede interna | C11: Obra 360 kW | D11: Validar protecao, seletividade, partida/VFD, fator de potencia >=0,92, banco de capacitores e medicao de demanda em 15 min.
B12: Modelo financeiro | C12: OPEX | D12: OPEX energia agora separa consumo ponta/fora ponta com impostos e demanda fixa A4 Verde 360 kW x 12 meses.
B13: Atualizacao do caso-base
B14: Caso-base combinado | C14: Operacao e contrato | D14: O modelo financeiro combina, como caso-base unico: cominuicao fora de ponta para reduzir consumo em HP + gestao ativa de demanda para manter demanda medida <= 360 kW.
B15: Pico sem gestao | C15: Alerta tecnico | D15: Cominuicao completa + pirolise estima ~370,45 kW. Isso nao deve ser tratado como rotina operacional livre; e um alerta para sequenciamento.
B16: Pico gerenciado | C16: Base financeira | D16: Com gestao ativa fixa no caso-base, o caso-base assume demanda maxima gerenciada em 360 kW e custo de demanda contratado 360 kW x 12 meses.
B17: Protocolo operacional | C17: Gestao de rede | D17: Evitar partida simultanea de motores grandes, escalonar fine crusher, acompanhar memoria de massa de 15 min e manter fator de potencia >=0,92.
B19: Meses sem operacao | C19: Contrato e OPEX | D19: O modelo trata consumo eletrico como custo apenas nos meses de operacao. A demanda contratada de 360 kW permanece custo fixo do projeto nos 12 meses, inclusive meses sem biomassa/processamento.

Sheet Serviços Astra Carbon
A2: Fase | B2: Item | C2: Entregáveis (escopo) | D2: Valor | E2: Obs
B3: Enquadramento no mercado voluntário de carbono | C3: Critérios gerais de integridade (mercado voluntário), premissas de elegibilidade e implicações para MRV. | D3: 32000
B4: Elegibilidade da área | C4: Analise de mudanças no uso do solo e comprovçao de posse | D4: 4000
B5: Disponibilidade e sazonalidade | C5: Diagnóstico de massa anual, umidade, granulometria e variações sazonais. | D5: 8000
B6: Logística preliminar | C6: Análise de Rotas/distâncias, densidade a granel/cavaco, capacidade de carga e cenários logísticos preliminares. | D6: 12000
B7: Compatibilidade biomassa × processo | C7: Compatibilidade com pré-tratamento, secagem, alimentação e estabilidade operacional. | D7: 12000
B8: Triagem de adicionalidade, elegibilidade e uso final | C8: Definição de linha de base, adicionalidade, elegibilidade, vazamentos e deslocamento e requisitos para aplicação do biochar no solo. | D8: 6000
B9: Permanência/durabilidade preliminar | C9: Estimativa preliminar de durabilidade (Fp/equivalente) com base em premissas de produto e aplicação. | D9: 5000
B10: Geração preliminar de biochar e créditos | C10: Estimativas preliminares de produção e créditos, com premissas transparentes. | D10: 6000
A11: Análise de Viabilidade | B11: Subtotal — Análise de Viabilidade | D11: =SUM(D3:D10) -> 85000
A12: Definição da tecnologia de pirólise | B12: Matriz comparativa de rotas termoquímicas | C12: Comparação entre carbonização, gaseificação, torrefação e pirólise (trade-offs técnicos e MRV). | D12: 6000
B13: Comparação por nível tecnológico | C13: Comparação entre baixa, média e alta tecnologia (qualidade, emissões, controle, replicabilidade). | D13: 8000
B14: Benchmark de fabricantes e modelos | C14: Análise comparativa (datasheets, performance, garantias, layout, pós-venda). | D14: 12000
B15: Risco de endosso/aceitação pelo padrão | C15: Análise de conformidade tecnológica com padrão-alvo (combustão de gases, controle e monitoramento). | D15: 3000
B16: Simulações CAPEX/OPEX por modelo | C16: Simulações financeiras por fabricante/modelo (CAPEX/OPEX/TCO) com premissas documentadas. | D16: 30000
B17: Requisitos técnicos do sistema – dimensionamento | C17: Requisitos por site: capacidade, regime de operação, energia, controles e emissões. | D17: 15000
B18: Pré-tratamento e manuseio (PIC/PENEIRA/SECAGEM/ARMAZ) | C18: Especificação de pré-tratamento e manuseio (picagem, peneiramento, secagem, armazenamento e alimentação). | D18: 20000
A19: Definição da tecnologia de pirólise | B19: Subtotal — Definição da tecnologia de pirólise | D19: =SUM(D12:D18) -> 94000
A20: Definição do padrão de certificação | B20: Due diligence de padrões/metodologias | C20: Análise de documentação, taxas e critérios: elegibilidade, adicionalidade, permanência, aplicação e MRV. - Sylvera | D20: 40000 | E20: Pago pela Viena
B21: Matriz comparativa + recomendação do padrão-alvo | C21: Matriz comparativa (feedstock, tecnologia, emissões, produto, uso e rastreabilidade) e recomendação. - Sylvera | D21: 55000 | E21: Pago pela Viena
B22: Arquitetura MRV + plano de evidências (templates) | C22: Estratégia MRV e plano de evidências padrão (checklists, trilha de auditoria, data room). | D22: 20000
B23: Simulações financeiras por padrão (estrutura) | C23: Estrutura de simulações comparativas: custos de estudos, taxas, MRV e auditorias por padrão. | D23: 8000
B24: Caminho de certificação e cronograma | C24: Caminho do projeto no padrão-alvo, milestones, entregáveis e cronograma por projeto. | D24: 12000
B25: Plano de evidências por projeto | C25: Adequação do plano de evidências ao contexto local (biomassa, operação, aplicação). | D25: 6000
B26: Preparação/coordenação para análise de terceira parte | C26: Preparação de narrativa, dados e submissões para avaliação de terceira parte (quando aplicável). | D26: 6000
A27: Definição do padrão de certificação | B27: Subtotal — Definição do padrão de certificação | D27: =SUM(D20:D26) -> 147000
A28: Modelo de negócios | B28: Estruturação do modelo de negócios (estratégia comercial) | C28: Definição de proposta de valor, produtos (biochar/créditos/co-produtos), canais e offtake. | D28: 120000
B29: Financiamento – mapeamento de linhas e requisitos | C29: Mapeamento de linhas de financiamento e entendimento de requisitos bancários para projetos. | D29: 18000
B30: Modelagem financeira + indicadores (FC, VPL, TIR, Payback) | C30: Projeção de fluxo de caixa e cálculo de indicadores financeiros com premissas do projeto. | D30: 20000
B31: Cenários logísticos, sensibilidade e otimização | C31: Simulações de cenários logísticos e sensibilidades (frete, densidade, umidade, disponibilidade). | D31: 30000
B32: Apoio em testes de campo (protocolo + relatório) | C32: Planejamento de coleta de dados, checklists e relatório técnico (suporte remoto). | D32: 30000
A33: Modelo de negócios | B33: Subtotal — Modelo de negócios | D33: =SUM(D28:D32) -> 218000
A34: Certificação | B34: Framework QMS/QA/QC + Data Room | C34: Sistema de gestão da qualidade documental, controle de versões, trilha de auditoria e estrutura de data room. | D34: 20000
B35: Templates MRV (SOPs, formulários e checklists) | C35: Conjunto mestre de ITs e formulários (pesagem, umidade, operação, lote, rastreabilidade, QA/QC). | D35: 15000
B36: Final PDD (+ anexos padrão) | C36: Estrutura e textos-base conforme template do padrão-alvo; anexos padrão e referências. | D36: 60000
B37: Governança pós-emissão (regras de lote, retenção, dados) | C37: Regras e processos para governança de dados e retenção de evidências pós-emissão. | D37: 25000
B38: Cadeia de custódia e origem legal | C38: Documentos de origem, cadeia de custódia, conformidade legal da biomassa residual e condiçoes de trabalho | D38: 12000
B39: Dossiê biomassa – sustentabilidade/manejo e evidências | C39: Evidências de manejo sustentável, políticas internas, controles e evidências complementares. | D39: 20000
B40: LCA – inventário (LCI) e coleta de dados primários | C40: Inventário cradle-to-grave: coleta e consolidação de dados (upstream, processo, downstream até aplicação/uso final). | D40: 5000
B41: LCA – modelagem e relatório auditável | C41: Modelagem e relatório auditável cradle-to-grave conforme ISO 14040/44 e requisitos do padrão (incl. sensibilidade). | D41: 35000
B42: LCA – revisões e resposta a comentários (pré-auditoria) | C42: Revisões internas + resposta a comentários (validação/verificação) e ajustes finais. | D42: 5000 | E42: Ainda não executado
B43: Plano MRV – desenho do sistema e responsabilidades | C43: Definição de rotinas, responsabilidades e fluxo de dados (biomassa → processo → lote → aplicação). (incl. cadeia de custódia até aplicação/uso final) | D43: 90000 | E43: Ainda não executado
B44: Plano MRV – treinamento inicial e handover | C44: Treinamento inicial e handover para operação assistida. | D44: 20000 | E44: Ainda não executado
B45: Plano laboratorial – parâmetros e periodicidade | C45: critérios do padrão, periodicidade e qualificação de laboratórios acreditados. | D45: 5000
B46: Preparação p/ validação/verificação do pacote de evidências | C46: Organização do pacote de evidências e data room do projeto para auditorias anuais | D46: 6000 | E46: Ainda não executado
B47: Preparação p/ validação/verificação – auditoria interna documental | C47: Auditoria interna documental, checagens finais e fechamento de gaps. | D47: 18000 | E47: Ainda não executado
B48: Suporte durante auditorias e fechamento de NCs | C48: Suporte técnico durante auditorias e fechamento de NCs. | D48: 20000 | E48: Ainda não executado
B49: Coordenação com VVB/padrão (Q&A e submissões intermediárias) | C49: Coordenação técnica para Q&A e submissões intermediárias com padrão/VVB. | D49: 20000 | E49: Ainda não executado
B50: Registro, emissão e governança operacional pós-emissão | C50: Suporte a registro/emissão e governança operacional (lotes, dados, retenção). | D50: 120000 | E50: Ainda não executado
A51: Certificação | B51: Subtotal — Certificação | D51: =SUMIF(E34:E50,"<>Ainda não executado",D34:D50) -> 197000
C52: Investimento Astra | D52: =SUM(D11,D19,D27,D33,D51) -> 741000
C53: Investimento Viena
C54: Capex Total | D54: =CAPEX!C16 -> 5498000
C55: Participação Astra | D55: =D52/(D54) -> 0.13477628

Sheet SENSIBILIDADE
A1: SENSIBILIDADE | Tabelas Bidimensionais
A2: Para análise completa, utilize a versão original ou a aba CENÁRIOS.

Sheet CENÁRIOS
B1: ANÁLISE DE CENÁRIOS | Inputs Editáveis → Resultados Dinâmicos
B2: Edite as células azuis. Coluna BASE espelha PREMISSAS centrais.
B4: Premissa / Indicador | C4: Unidade | D4: CONSERVADOR | E4: BASE | F4: OTIMISTA | G4: PREMIUM
B5: A — PREMISSAS DE ENTRADA
B6: Preço crédito carbono | C6: USD/tCO₂e | D6: 120 | E6: =PREMISSAS!$C$30 -> 170 | F6: 250 | G6: 320
B7: Fração mássica resíduo (Pincelli) | C7: % | D7: 0.04 | E7: =PREMISSAS!$C$7 -> 0.06 | F7: 0.08 | G7: 0.1
B8: Rendimento de pirólise | C8: % | D8: 0.27 | E8: =PREMISSAS!$C$26 -> 0.3 | F8: 0.33 | G8: 0.35
B9: Multiplicador de CAPEX | C9: × | D9: 1.2 | E9: 1 | F9: 0.9 | G9: 0.9
B10: Taxa de desconto (WACC) | C10: % | D10: 0.12 | E10: =PREMISSAS!$C$101 -> 0.1 | F10: 0.1 | G10: 0.08
B11: Modalidade eletrica | C11: contrato | D11: A4 Verde 360 kW | E11: =PREMISSAS!$C$47 -> Cemig A4 Verde 360 kW | F11: A4 Verde 360 kW | G11: A4 Verde 360 kW
B12: Energia eletrica | C12: nota | D12: Fixa no caso-base: sem cenarios A/B eletricos | E12: Cominuicao fora ponta + gestao demanda | F12: Fixa | G12: Fixa
B13: B — RESULTADOS (requerem simulação manual)
B14: Para resultados, altere inputs em PREMISSAS e observe INDICADORES.

Sheet Dashboard
A1: DASHBOARD DINÂMICO — atualiza com premissas do modelo
A2: Tabelas de apoio abaixo alimentam os gráficos. Não editar manualmente — todas as células contêm fórmulas vinculadas ao modelo.
A4: CAPEX BREAKDOWN | E4: OPEX BREAKDOWN (anual)
A5: Item | B5: Valor (R$) | C5: % Total | E5: Item | F5: Valor (R$/ano) | G5: Categoria
A6: =CAPEX!B6 -> Reator de pirólise BST-30 | B6: =CAPEX!C6 -> 2210000 | C6: =CAPEX!D6 -> 0.40196435 | E6: =OPEX!B12 -> Mao de obra operacional | F6: =OPEX!F12 -> 354675.83 | G6: Por mês de campanha
A7: =CAPEX!B15 -> Serviços Astra Carbon | B7: =CAPEX!C15 -> 741000 | C7: =CAPEX!D15 -> 0.13477628 | E7: =OPEX!B5 -> Energia eletrica variavel - somente meses com operacao | F7: =OPEX!F5 -> 624196.09 | G7: Por tonelada
A8: =CAPEX!B10 -> Montagem e comissionamento | B8: =CAPEX!C10 -> 450000 | C8: =CAPEX!D10 -> 0.081847945 | E8: =OPEX!B7 -> Logistica de transporte | F8: =OPEX!F7 -> 236450.55 | G8: Por tonelada
A9: =CAPEX!B5 -> Infraestrutura civil | B9: =CAPEX!C5 -> 400000 | C9: =CAPEX!D5 -> 0.072753729 | E9: =OPEX!B16 -> Demanda contratada Cemig A4 Verde 360 kW - 12 meses | F9: =OPEX!F16 -> 129214.79 | G9: Fixo anual
A10: =CAPEX!B13 -> Plano de MRV e data room | B10: =CAPEX!C13 -> 150000 | C10: =CAPEX!D13 -> 0.027282648 | E10: =OPEX!B6 -> Logistica de coleta | F10: =OPEX!F6 -> 141870.33 | G10: Por tonelada
A11: =CAPEX!B9 -> Frete + seguro + sobressalentes | B11: =CAPEX!C9 -> 312000 | C11: =CAPEX!D9 -> 0.056747908 | E11: =OPEX!B17 -> Auditoria e verificacao anual | F11: =OPEX!F17 -> 100000 | G11: Fixo anual
A12: =CAPEX!B4 -> Terraplanagem e drenagem | B12: =CAPEX!C4 -> 300000 | C12: =CAPEX!D4 -> 0.054565296 | E12: =OPEX!B13 -> O&M reator BST-30 | F12: =OPEX!F13 -> 22100 | G12: Por mês de campanha
A13: =CAPEX!B3 -> Instalação elétrica | B13: =CAPEX!C3 -> 0 | C13: =CAPEX!D3 -> 0 | E13: =OPEX!B18 -> Renovacao LCA + relatorio | F13: =OPEX!F18 -> 35000 | G13: Fixo anual
A14: =CAPEX!B7 -> Linha de cominuição / triturador | B14: =CAPEX!C7 -> 240000 | C14: =CAPEX!D7 -> 0.043652237 | E14: =OPEX!B9 -> Material de laboratorio | F14: =OPEX!F9 -> 36094.177 | G14: Por tonelada
A15: =CAPEX!B8 -> Secador de biomassa | B15: =CAPEX!C8 -> 150000 | C15: =CAPEX!D8 -> 0.027282648 | E15: =OPEX!B8 -> Big bags e embalagem | F15: =OPEX!F8 -> 25264.741 | G15: Por tonelada
A16: =CAPEX!B14 -> Auditoria e certificação inicial | B16: =CAPEX!C14 -> 100000 | C16: =CAPEX!D14 -> 0.018188432 | E16: =OPEX!B19 -> Treinamento e outros fixos | F16: =OPEX!F19 -> 10000 | G16: Fixo anual
A17: =CAPEX!B12 -> Análise de Ciclo de Vida (ACV) | B17: =CAPEX!C12 -> 45000 | C17: =CAPEX!D12 -> 0.0081847945 | E17: TOTAL | F17: =OPEX!F22 -> 1734535.5
A18: TOTAL | B18: =CAPEX!C16 -> 5498000 | C18: 1
A21: EBITDA CASCATA — Cenário Atual do Modelo (atualiza com Astra% e demais premissas)
A23: Etapa | B23: Invisible | C23: Aumento | D23: Diminuição | E23: Total
A24: Receita | B24: 0 | C24: 0 | D24: 0 | E24: =DRE_FCL!F5 -> 2897370.5
A25: (−) Astra | B25: =DRE_FCL!F5+DRE_FCL!F6 -> 2897370.5 | C25: 0 | D25: =-DRE_FCL!F6 -> 0 | E25: 0
A26: (−) OPEX | B26: =DRE_FCL!F8 -> 1162835 | C26: 0 | D26: =-DRE_FCL!F7 -> 1734535.5 | E26: 0
A27: EBITDA | B27: 0 | C27: 0 | D27: 0 | E27: =DRE_FCL!F8 -> 1162835
A28: (−) D&A | B28: =DRE_FCL!F11 -> 939734.97 | C28: 0 | D28: =-DRE_FCL!F10 -> 223100 | E28: 0
A29: EBIT | B29: 0 | C29: 0 | D29: 0 | E29: =DRE_FCL!F11 -> 939734.97
A30: (−) Tributos | B30: =DRE_FCL!F13 -> 376218.31 | C30: 0 | D30: =-DRE_FCL!F12 -> 563516.66 | E30: 0
A31: Lucro Líq. | B31: 0 | C31: 0 | D31: 0 | E31: =DRE_FCL!F13 -> 376218.31
A32: (+) D&A | B32: =DRE_FCL!F13 -> 376218.31 | C32: =DRE_FCL!F14 -> 223100 | D32: 0 | E32: 0
A33: FCL | B33: 0 | C33: 0 | D33: 0 | E33: =DRE_FCL!F15 -> 599318.31
A35: FCL ACUMULADO — Cenário Atual do Modelo
A36: Ano | B36: FCL Anual | C36: FCL Acumulado | D36: Breakeven | E36: Zero | G36: Breakeven Ano | H36: =IFERROR(_xlfn.AGGREGATE(15,6,A37:A57/(C37:C57>=0),1),"-") -> 2037
A37: =DRE_FCL!E3 -> 2026 | B37: =DRE_FCL!E15 -> -5498000 | C37: =B37 -> -5498000 | D37: =IF(C37>=0,C37,NA()) -> #N/A | E37: 0 | G37: Astra % | H37: =PREMISSAS!C102 -> 0
A38: =DRE_FCL!F3 -> 2027 | B38: =DRE_FCL!F15 -> 599318.31 | C38: =C37+B38 -> -4898681.7 | D38: =IF(AND(C38>=0,C37<0),C38,NA()) -> #N/A | E38: 0 | G38: Título dinâmico | H38: ="FCL Acumulado — 2025 a 2045 (Breakeven "&H36&" ~ Astra "&TEXT(H37,"0%")&")" -> FCL Acumulado — 2025 a 2045 (Breakeven 2037 ~ Astra 0%)
A39: =DRE_FCL!G3 -> 2028 | B39: =DRE_FCL!G15 -> 584732.31 | C39: =C38+B39 -> -4313949.4 | D39: =IF(AND(C39>=0,C38<0),C39,NA()) -> #N/A | E39: 0
A40: =DRE_FCL!H3 -> 2029 | B40: =DRE_FCL!H15 -> 570146.31 | C40: =C39+B40 -> -3743803.1 | D40: =IF(AND(C40>=0,C39<0),C40,NA()) -> #N/A | E40: 0
A41: =DRE_FCL!I3 -> 2030 | B41: =DRE_FCL!I15 -> 555560.31 | C41: =C40+B41 -> -3188242.7 | D41: =IF(AND(C41>=0,C40<0),C41,NA()) -> #N/A | E41: 0
A42: =DRE_FCL!J3 -> 2031 | B42: =DRE_FCL!J15 -> 540974.31 | C42: =C41+B42 -> -2647268.4 | D42: =IF(AND(C42>=0,C41<0),C42,NA()) -> #N/A | E42: 0
A43: =DRE_FCL!K3 -> 2032 | B43: =DRE_FCL!K15 -> 526388.31 | C43: =C42+B43 -> -2120880.1 | D43: =IF(AND(C43>=0,C42<0),C43,NA()) -> #N/A | E43: 0
A44: =DRE_FCL!L3 -> 2033 | B44: =DRE_FCL!L15 -> 511802.31 | C44: =C43+B44 -> -1609077.8 | D44: =IF(AND(C44>=0,C43<0),C44,NA()) -> #N/A | E44: 0
A45: =DRE_FCL!M3 -> 2034 | B45: =DRE_FCL!M15 -> 497216.31 | C45: =C44+B45 -> -1111861.5 | D45: =IF(AND(C45>=0,C44<0),C45,NA()) -> #N/A | E45: 0
A46: =DRE_FCL!N3 -> 2035 | B46: =DRE_FCL!N15 -> 482630.31 | C46: =C45+B46 -> -629231.18 | D46: =IF(AND(C46>=0,C45<0),C46,NA()) -> #N/A | E46: 0
A47: =DRE_FCL!O3 -> 2036 | B47: =DRE_FCL!O15 -> 468044.31 | C47: =C46+B47 -> -161186.87 | D47: =IF(AND(C47>=0,C46<0),C47,NA()) -> #N/A | E47: 0
A48: =DRE_FCL!P3 -> 2037 | B48: =DRE_FCL!P15 -> 468044.31 | C48: =C47+B48 -> 306857.44 | D48: =IF(AND(C48>=0,C47<0),C48,NA()) -> 306857.44 | E48: 0
A49: =DRE_FCL!Q3 -> 2038 | B49: =DRE_FCL!Q15 -> 468044.31 | C49: =C48+B49 -> 774901.76 | D49: =IF(AND(C49>=0,C48<0),C49,NA()) -> #N/A | E49: 0
A50: =DRE_FCL!R3 -> 2039 | B50: =DRE_FCL!R15 -> 468044.31 | C50: =C49+B50 -> 1242946.1 | D50: =IF(AND(C50>=0,C49<0),C50,NA()) -> #N/A | E50: 0
A51: =DRE_FCL!S3 -> 2040 | B51: =DRE_FCL!S15 -> 468044.31 | C51: =C50+B51 -> 1710990.4 | D51: =IF(AND(C51>=0,C50<0),C51,NA()) -> #N/A | E51: 0
A52: =DRE_FCL!T3 -> 2041 | B52: =DRE_FCL!T15 -> 468044.31 | C52: =C51+B52 -> 2179034.7 | D52: =IF(AND(C52>=0,C51<0),C52,NA()) -> #N/A | E52: 0
A53: =DRE_FCL!U3 -> 2042 | B53: =DRE_FCL!U15 -> 468044.31 | C53: =C52+B53 -> 2647079 | D53: =IF(AND(C53>=0,C52<0),C53,NA()) -> #N/A | E53: 0
A54: =DRE_FCL!V3 -> 2043 | B54: =DRE_FCL!V15 -> 468044.31 | C54: =C53+B54 -> 3115123.3 | D54: =IF(AND(C54>=0,C53<0),C54,NA()) -> #N/A | E54: 0
A55: =DRE_FCL!W3 -> 2044 | B55: =DRE_FCL!W15 -> 468044.31 | C55: =C54+B55 -> 3583167.6 | D55: =IF(AND(C55>=0,C54<0),C55,NA()) -> #N/A | E55: 0
A56: =DRE_FCL!X3 -> 2045 | B56: =DRE_FCL!X15 -> 468044.31 | C56: =C55+B56 -> 4051211.9 | D56: =IF(AND(C56>=0,C55<0),C56,NA()) -> #N/A | E56: 0
A57: =DRE_FCL!Y3 -> 2046 | B57: =DRE_FCL!Y15 -> 468044.31 | C57: =C56+B57 -> 4519256.3 | D57: =IF(AND(C57>=0,C56<0),C57,NA()) -> #N/A | E57: 0

Sheet GraficosV8
A1: DRE 2026 - Cenario base eletrico unico (A4 Verde 360 kW | 207,9 kWh/t | Alimentacao: 3.594 t/ano)
A3: Linha DRE | B3: Cenário A (fee 0%) | C3: Cenário B (fee 10%)
A4: Receita bruta | B4: 2378161.7 | C4: 2378161.7
A5: (–) Fee Astra | B5: 0 | C5: -237816.17
A6: (–) OPEX total | B6: -1733139 | C6: -1733139
A7: EBITDA | B7: 645022.72 | C7: 407206.55
A8: (–) Depreciação | B8: -324312.5 | C8: -254100
A9: EBIT | B9: 320710.22 | C9: 153106.55
A10: (–) Tributos | B10: -85041.48 | C10: -36745.57
A11: Lucro líquido | B11: 235668.75 | C11: 116360.98
A14: FCL Acumulado 2025–2045 (R$) | E14: Sensibilidade: Cenário × Modo de operação
A16: Ano | B16: Cenário A (fee 0%) | C16: Cenário B (fee 10%) | E16: Combinação | F16: VPL @ 10% | G16: TIR | H16: EBITDA médio
A17: 2026 | B17: -5274125 | C17: -4572000 | E17: Cenário A — referencia antiga removida | F17: -1678052.6 | G17: 0.0432 | H17: 438082.73
A18: 2027 | B18: -4714143.8 | C18: -4201539 | E18: Cenário A — caso-base eletrico | F18: -549382.41 | G18: 0.0825 | H18: 645022.72
A19: 2028 | B19: -4154162.5 | C19: -3831078 | E19: Cenário B — referencia antiga removida | F19: -2606379.9 | G19: -0.0123 | H19: 200266.56
A20: 2029 | B20: -3594181.3 | C20: -3460617.1 | E20: Cenário B — caso-base eletrico | F20: -1315503 | G20: 0.0497 | H20: 407206.55
A21: 2030 | B21: -3034200 | C21: -3090156.1
A22: 2031 | B22: -2474218.8 | C22: -2719695.1
A23: 2032 | B23: -1914237.5 | C23: -2349234.1
A24: 2033 | B24: -1354256.3 | C24: -1978773.1
A25: 2034 | B25: -794275.02 | C25: -1608312.1
A26: 2035 | B26: -234293.77 | C26: -1237851.2
A27: 2036 | B27: 325687.48 | C27: -867390.19
A28: 2037 | B28: 844456.47 | C28: -509169.2
A29: 2038 | B29: 1363225.5 | C29: -150948.22
A30: 2039 | B30: 1881994.5 | C30: 207272.76
A31: 2040 | B31: 2400763.5 | C31: 565493.74
A32: 2041 | B32: 2919532.5 | C32: 923714.72
... A37: 2046 | B37: 5513377.5 | C37: 2714819.6
